{"tmdb_id":207836,"name":"House of Hammer","original_name":"House of Hammer","first_air_date":"2022-09-02","overview":"A shocking Hollywood scandal rips open the Hammer family's perfect fa\u00e7ade. From rape allegations against Armie Hammer to years of deceit at the hands of his great-grandfather, the family's dark secrets finally come to light.","poster_path":"/3BYEyu9Ej4oSywd8yjUTbMJkBzY.jpg","backdrop_path":"/1jgR2LI3MxmbG5lMpMUCF02sOz.jpg","status":"Ended","number_of_seasons":1,"vote_average":6.8,"vote_count":44,"original_language":"en","genres":["Documentary"],"slug":"house-of-hammer-207836","trailers":[{"youtube_id":"FIQ80m7831I","title":"Official Trailer","trailer_type":"trailer","language":"en","region":"US","is_official":true,"published_at":"2022-08-09T23:24:07.000Z","quality":1080}]}