{"tmdb_id":278509,"name":"Lost in LA","original_name":"Lost in LA","first_air_date":"2013-10-23","overview":"Candace Benson has packed up and moved to LA to make it in Hollywood. She and her best friend Bridgett quickly realize it's not what it's cracked up to be.. Further along, Candace meets all sorts of misfits that guide her along a shaky path.","poster_path":"/uo1yODlX2lOEyydVIznvOdQPjFO.jpg","backdrop_path":"/mt7vUkQ5DWP4S3oCsEWn8qJ0gOY.jpg","status":"Ended","number_of_seasons":3,"vote_average":0.0,"vote_count":0,"original_language":"en","genres":["Comedy"],"slug":"lost-in-la-278509","trailers":[{"youtube_id":"8P5nrKFSaFM","title":"LOST IN LA - TRAILER for Season 1 & 2","trailer_type":"trailer","language":"en","region":"US","is_official":false,"published_at":"2015-07-04T00:21:19.000Z","quality":1080}]}