{"tmdb_id":66061,"name":"Lopez","original_name":"Lopez","first_air_date":"2016-03-30","overview":"Exploring the real George Lopez we rarely get to see, pushed and pulled between the worlds of race, class and fame, yet always having a hard time fitting in.","poster_path":"/glTy9mlo0a448ORYfyZAvr7fY8I.jpg","backdrop_path":"/lLhQLoIxncg3NSaDIrYywEKiuLW.jpg","status":"Canceled","number_of_seasons":2,"vote_average":5.4,"vote_count":10,"original_language":"en","genres":["Comedy"],"slug":"lopez-66061","trailers":[{"youtube_id":"IocZXfw79Cc","title":"Lopez On TV Land Extended Trailer","trailer_type":"trailer","language":"en","region":"US","is_official":true,"published_at":"2016-03-10T22:16:57.000Z","quality":720}]}