{"imdb_id":"tt0076111","tmdb_id":69903,"title":"The Greatest","original_title":"The Greatest","year":1977,"release_date":null,"imdb_rating":5.9,"imdb_votes":1770,"runtime":102,"overview":"Muhammad Ali's life story up to the late 1970s, which includes his Olympic boxing triumphs as Cassius Clay, his conversion to Islam, his refusal of the Army draft and the legal battle after being stripped of his World Title.","poster_path":"/dkPVN51q9hbzkN5zmwybsLMhCej.jpg","backdrop_path":"/w9Sc3NcIhOV4zHbjNTcmOFKEwhq.jpg","original_language":"en","genres":["Drama"],"slug":"the-greatest-1977-tt0076111","trailers":[{"youtube_id":"5DUT6X7Wbjk","title":"Muhammad Ali - The Greatest 1977) TRAILER","type":"trailer","language":"en","region":"US","is_official":true,"published_at":"2013-09-20T06:58:43.000Z","quality":360,"channel_name":"Umbrella Entertainment","duration":181,"views":34693}],"trailer_groups":[{"group_id":942795,"type":"trailer","title":"Muhammad Ali - The Greatest 1977) TRAILER","languages":{"en":{"youtube_id":"5DUT6X7Wbjk","title":"Muhammad Ali - The Greatest 1977) TRAILER"}}}]}