{"imdb_id":"tt0084058","tmdb_id":67794,"title":"Heat and Dust","original_title":"Heat and Dust","year":1983,"release_date":null,"imdb_rating":6.5,"imdb_votes":2367,"runtime":133,"overview":"Anne is investigating the life of her grand-aunt Olivia, whose destiny has always been shrouded with scandal. As Anne delves into the history of her grand-aunt, she is led to reconsider her own life.","poster_path":"/97SCmQDukEQlyCnM7R3PvxhAgMW.jpg","backdrop_path":"/6YuxS3EY13Dqyu0holYCRoZrHdk.jpg","original_language":"en","genres":["Drama","Romance"],"slug":"heat-and-dust-1983-tt0084058","trailers":[{"youtube_id":"8Q39fIVE9WQ","title":"Heat and Dust (1983) ORIGINAL TRAILER [HD]","type":"trailer","language":"en","region":"US","is_official":false,"published_at":"2020-08-19T10:00:02.000Z","quality":1080,"channel_name":"HD Retro Trailers","duration":99,"views":40127}],"trailer_groups":[{"group_id":934037,"type":"trailer","title":"Heat and Dust (1983) ORIGINAL TRAILER [HD]","languages":{"en":{"youtube_id":"8Q39fIVE9WQ","title":"Heat and Dust (1983) ORIGINAL TRAILER [HD]"}}}]}