{"imdb_id":"tt0059749","tmdb_id":13580,"title":"The Spy Who Came in from the Cold","original_title":"The Spy Who Came In from the Cold","year":1965,"release_date":null,"imdb_rating":7.5,"imdb_votes":20611,"runtime":112,"overview":"British agent Alec Leamas refuses to come in from the Cold War during the 1960s, choosing to face another mission, which may prove to be his final one.","poster_path":"/lN3PWv6cW22mqXDcgGZgK1Aa2gh.jpg","backdrop_path":"/llwusQFdHmHCWS7jySP2r6bbAIm.jpg","original_language":"en","genres":["Drama","Thriller"],"slug":"the-spy-who-came-in-from-the-cold-1965-tt0059749","trailers":[{"youtube_id":"vlYK9AoQlOc","title":"The Spy Who Came in From the Cold - Trailer","type":"trailer","language":"en","region":"US","is_official":true,"published_at":"2014-10-09T23:51:36.000Z","quality":480,"channel_name":"Paramount Movies Digital","duration":91,"views":14499},{"youtube_id":"52_3k1R3O9Q","title":"THE SPY WHO CAME IN FROM THE COLD Trailer [1965] 4K","type":"trailer","language":"en","region":"US","is_official":false,"published_at":"2023-02-10T20:34:58.000Z","quality":2160,"channel_name":"Vintage Movie Trailers","duration":98,"views":9459},{"youtube_id":"ixTaTXAvcqs","title":"The Spy Who Came in from the Cold \u2263 1965 \u2263 Trailer","type":"trailer","language":"en","region":"US","is_official":false,"published_at":"2022-11-30T11:23:59.000Z","quality":1080,"channel_name":"TrailerTrackerEnglish","duration":90,"views":291},{"youtube_id":"xbJzf7PkgMg","title":"L'espion qui venait du froid","type":"trailer","language":"fr","region":"FR","is_official":false,"published_at":"2017-06-23T04:58:17.000Z","quality":480,"channel_name":"cinemaetcie","duration":91,"views":558},{"youtube_id":"KOgMAzpZpJs","title":"L'espion qui venait du froid (1965) bande annonce","type":"trailer","language":"fr","region":"FR","is_official":false,"published_at":"2016-03-22T15:20:22.000Z","quality":480,"channel_name":"imineo Bandes Annonces","duration":87,"views":9339},{"youtube_id":"aAR8YUCnG8o","title":"John le Carr\u00e9 - Where Alec Leamas Came From - The Spy Who Came in From the Cold","type":"featurette","language":"en","region":"US","is_official":true,"published_at":"2013-10-01T14:19:36.000Z","quality":1080,"channel_name":"CRITERION","duration":61,"views":39083}],"trailer_groups":[{"group_id":875521,"type":"featurette","title":"John le Carr\u00e9 - Where Alec Leamas Came From - The Spy Who Came in From the Cold","languages":{"en":{"youtube_id":"aAR8YUCnG8o","title":"John le Carr\u00e9 - Where Alec Leamas Came From - The Spy Who Came in From the Cold"}}},{"group_id":875522,"type":"trailer","title":"The Spy Who Came in From the Cold - Trailer","languages":{"en":{"youtube_id":"vlYK9AoQlOc","title":"The Spy Who Came in From the Cold - Trailer"}}},{"group_id":875523,"type":"trailer","title":"L'espion qui venait du froid (1965) bande annonce","languages":{"fr":{"youtube_id":"KOgMAzpZpJs","title":"L'espion qui venait du froid (1965) bande annonce"}}},{"group_id":875524,"type":"trailer","title":"L'espion qui venait du froid","languages":{"fr":{"youtube_id":"xbJzf7PkgMg","title":"L'espion qui venait du froid"}}},{"group_id":875525,"type":"trailer","title":"The Spy Who Came in from the Cold \u2263 1965 \u2263 Trailer","languages":{"en":{"youtube_id":"ixTaTXAvcqs","title":"The Spy Who Came in from the Cold \u2263 1965 \u2263 Trailer"}}},{"group_id":875526,"type":"trailer","title":"THE SPY WHO CAME IN FROM THE COLD Trailer [1965] 4K","languages":{"en":{"youtube_id":"52_3k1R3O9Q","title":"THE SPY WHO CAME IN FROM THE COLD Trailer [1965] 4K"}}}]}