{"imdb_id":"tt0111732","tmdb_id":16297,"title":"With Honors","original_title":"With Honors","year":1994,"release_date":null,"imdb_rating":6.7,"imdb_votes":18108,"runtime":103,"overview":"Convinced he'll graduate with honors because of his thesis paper, a stuffy Harvard student finds his paper being held hostage by a homeless man, who might be the guy to school the young man in life.","poster_path":"/eWJ2Y7CRvlv1KVfAJGRcH95i1pY.jpg","backdrop_path":"/m0m0ikotUirpFBRuqjfXA738CMc.jpg","original_language":"en","genres":["Comedy","Drama"],"slug":"with-honors-1994-tt0111732","trailers":[{"youtube_id":"DZ7Fm26YJjs","title":"With Honors (1994) Official Trailer - Joe Pesci, Brendan Fraser Movie HD","type":"trailer","language":"en","region":"US","is_official":false,"published_at":"2014-07-16T06:30:21.000Z","quality":720,"channel_name":"Rotten Tomatoes Classic Trailers","duration":122,"views":422616},{"youtube_id":"tWMwABOTRjQ","title":"With Honors (1994) Teaser (VHS Capture)","type":"teaser","language":"en","region":"US","is_official":false,"published_at":"2015-07-20T17:53:58.000Z","quality":480,"channel_name":"retro VHS trailers","duration":31,"views":19217}],"trailer_groups":[{"group_id":879027,"type":"teaser","title":"With Honors (1994) Teaser (VHS Capture)","languages":{"en":{"youtube_id":"tWMwABOTRjQ","title":"With Honors (1994) Teaser (VHS Capture)"}}},{"group_id":879028,"type":"trailer","title":"With Honors (1994) Official Trailer - Joe Pesci, Brendan Fraser Movie HD","languages":{"en":{"youtube_id":"DZ7Fm26YJjs","title":"With Honors (1994) Official Trailer - Joe Pesci, Brendan Fraser Movie HD"}}}]}