{"imdb_id":"tt0829432","tmdb_id":148665,"title":"Me & You, Us, Forever","original_title":"Me & You, Us, Forever","year":2008,"release_date":null,"imdb_rating":4.5,"imdb_votes":276,"runtime":104,"overview":"A 47 year old Christian man on the other side of an unwanted divorce thinks back on his first love from high school and wants to see her again.","poster_path":"/u4b5waxz5jeRctnaP2sAZMXzQM6.jpg","backdrop_path":"/dckyPWJGhFwSBhX9VhRwdqHkQwN.jpg","original_language":"en","genres":["Drama"],"slug":"me-you-us-forever-2008-tt0829432","trailers":[{"youtube_id":"QkFyqlkbwK4","title":"Me & You, Us, Forever","type":"trailer","language":"en","region":"US","is_official":false,"published_at":"2017-09-27T01:52:34.000Z","quality":1080,"channel_name":"YouTube Movies","duration":59,"views":9351},{"youtube_id":"xBGl6YAfjWU","title":"Me & You, Us, Forever - Movie Trailer (Dave Christiano Films)","type":"trailer","language":"en","region":"US","is_official":false,"published_at":"2017-06-11T02:14:22.000Z","quality":720,"channel_name":"Christian Movies","duration":62,"views":29319}],"trailer_groups":[{"group_id":992990,"type":"trailer","title":"Me & You, Us, Forever - Movie Trailer (Dave Christiano Films)","languages":{"en":{"youtube_id":"xBGl6YAfjWU","title":"Me & You, Us, Forever - Movie Trailer (Dave Christiano Films)"}}},{"group_id":992991,"type":"trailer","title":"Me & You, Us, Forever","languages":{"en":{"youtube_id":"QkFyqlkbwK4","title":"Me & You, Us, Forever"}}}]}