{"imdb_id":"tt10613838","tmdb_id":510273,"title":"Mata Dewa","original_title":"Mata Dewa","year":2018,"release_date":null,"imdb_rating":7.1,"imdb_votes":20,"runtime":80,"overview":"Dewa (Kenny Austin) wants to bring his school, Wijaya High School, becomes the first DBL champion. Dewa and his team are assisted by coach Miko (Nino Fernandez). Bumi (Brandon Salim), the supporter coordinator, is always in the stands to lead his friends. Bening (Agatha Chelsea), high school journalist Wijaya, actively participates in the journey of Wijaya High School basketball team. Dewa\u2019s heart who is an arrogant boy, dissolves. Disaster strikes Dewa, while helping Bening from mugging. His left eye was beaten by thugs. As a result, the eye can not function properly. Dewa is broken. A former veteran boxer (Ariyo Wahab) who lives across from his uncle's (Dodit Mulyanto) apartment, helps Dewa from deterioration.","poster_path":"/lZnvuQvpAK8x3ZyhwfoWriSZDqW.jpg","backdrop_path":null,"original_language":"id","genres":["Drama"],"slug":"mata-dewa-2018-tt10613838","trailers":[{"youtube_id":"zpCEX7-DHJs","title":"Mata Dewa The Movie Trailer - Tayang 8 Maret 2018","type":"trailer","language":"en","region":"US","is_official":false,"published_at":"2018-01-24T15:22:17.000Z","quality":1080,"channel_name":"Mata Dewa","duration":134,"views":520327}],"trailer_groups":[{"group_id":1038093,"type":"trailer","title":"Mata Dewa The Movie Trailer - Tayang 8 Maret 2018","languages":{"en":{"youtube_id":"zpCEX7-DHJs","title":"Mata Dewa The Movie Trailer - Tayang 8 Maret 2018"}}}]}