{"imdb_id":"tt11563598","tmdb_id":661539,"title":"A Complete Unknown","original_title":"A Complete Unknown","year":2024,"release_date":null,"imdb_rating":7.3,"imdb_votes":115700,"runtime":140,"overview":"New York, early 1960s. Against the backdrop of a vibrant music scene and tumultuous cultural upheaval, an enigmatic 19-year-old from Minnesota arrives in the West Village with his guitar and revolutionary talent, destined to change the course of American music.","poster_path":"/llWl3GtNoXosbvYboelmoT459NM.jpg","backdrop_path":"/kcCy5tKTe6WepVQ6SQaSewpmoCj.jpg","original_language":"en","genres":["Drama","Music"],"slug":"a-complete-unknown-2024-tt11563598","trailers":[{"youtube_id":"ob4SHtT6cC0","title":"Be the first to watch at home, nominated for 8 Academy Awards\u00ae.","type":"trailer","language":"en","region":"US","is_official":true,"published_at":"2025-02-11T16:00:49.000Z","quality":1080,"channel_name":"SearchlightPictures","duration":85,"views":75266},{"youtube_id":"YLYNZ4jDcdk","title":"Nuevo Tr\u00e1iler en espa\u00f1ol","type":"trailer","language":"es","region":"ES","is_official":true,"published_at":"2025-01-24T11:39:58.000Z","quality":1080,"channel_name":"20th Century Studios Espa\u00f1a","duration":76,"views":287187},{"youtube_id":"NdQbdU7H8kg","title":"\uba54\uc778 \uc608\uace0\ud3b8","type":"trailer","language":"ko","region":"KR","is_official":true,"published_at":"2025-01-21T23:00:14.000Z","quality":1080,"channel_name":"20th Century Studios Korea","duration":154,"views":284642},{"youtube_id":"KuVnRN_LVOw","title":"A Complete Unknown | Trailer Finale | Dal 23 Gennaio al Cinema","type":"trailer","language":"it","region":"IT","is_official":true,"published_at":"2025-01-13T12:17:35.000Z","quality":1080,"channel_name":"Searchlight Pictures Italia","duration":76,"views":12903},{"youtube_id":"NO9hXSD5K4A","title":"Final Trailer","type":"trailer","language":"en","region":"US","is_official":true,"published_at":"2024-12-23T16:03:31.000Z","quality":1080,"channel_name":"SearchlightPictures","duration":76,"views":751087},{"youtube_id":"syxd43MuBC4","title":"Tam Bir Bilinmez | \u0130lk Fragman","type":"trailer","language":"tr","region":"TR","is_official":true,"published_at":"2024-11-11T10:01:00.000Z","quality":1080,"channel_name":"Disney Studios T\u00fcrkiye","duration":145,"views":8295},{"youtube_id":"Nb_Gvv52-EI","title":"UN PARFAIT INCONNU | Bande-annonce officielle | FR","type":"trailer","language":"fr","region":"FR","is_official":true,"published_at":"2024-10-29T15:02:56.000Z","quality":1080,"channel_name":"20th Century Studios & Searchlight Pictures CH","duration":145,"views":30409},{"youtube_id":"nyIknvGt8Lg","title":"Like A Complete Unknown I Offizieller Trailer I Ab 27. Februar nur im Kino","type":"trailer","language":"de","region":"DE","is_official":true,"published_at":"2024-10-29T13:12:26.000Z","quality":1080,"channel_name":"20th Century Studios DE","duration":147,"views":70523},{"youtube_id":"ilkdlJ_Nh0A","title":"\u4e88\u544a\u6620\u50cf\uff08\u5b57\u5e55\u7248\uff09","type":"trailer","language":"ja","region":"JP","is_official":true,"published_at":"2024-10-28T02:00:46.000Z","quality":1080,"channel_name":"\u30b5\u30fc\u30c1\u30e9\u30a4\u30c8\u30fb\u30d4\u30af\u30c1\u30e3\u30fc\u30ba","duration":147,"views":316117},{"youtube_id":"pHvskfTszoU","title":"A Complete Unknown | Trailer Ufficiale","type":"trailer","language":"it","region":"IT","is_official":true,"published_at":"2024-10-11T09:08:37.000Z","quality":1080,"channel_name":"Searchlight Pictures Italia","duration":145,"views":157796},{"youtube_id":"LmoNBGdeoyw","title":"Tr\u00e1iler Oficial [VOSE]","type":"trailer","language":"es","region":"ES","is_official":true,"published_at":"2024-10-10T11:04:55.000Z","quality":1080,"channel_name":"20th Century Studios Espa\u00f1a","duration":145,"views":3090},{"youtube_id":"5WGNuAR__NM","title":"Tr\u00e1iler oficial en espa\u00f1ol","type":"trailer","language":"es","region":"ES","is_official":true,"published_at":"2024-10-09T08:40:55.000Z","quality":1080,"channel_name":"20th Century Studios Espa\u00f1a","duration":145,"views":164391},{"youtube_id":"lbwhookIZ2c","title":"A COMPLETE UNKNOWN l Trailer","type":"trailer","language":"sv","region":"SE","is_official":true,"published_at":"2024-10-09T06:36:00.000Z","quality":1080,"channel_name":"20th Century Studios Sverige","duration":145,"views":4289},{"youtube_id":"8R7LCOLLZA0","title":"A COMPLETE UNKNOWN l Traileri","type":"trailer","language":"fi","region":"FI","is_official":true,"published_at":"2024-10-08T13:38:37.000Z","quality":1080,"channel_name":"Twentieth Century Studios Suomi","duration":145,"views":14209},{"youtube_id":"FdV-Cs5o8mc","title":"Official Trailer","type":"trailer","language":"en","region":"US","is_official":true,"published_at":"2024-10-08T13:00:10.000Z","quality":1080,"channel_name":"SearchlightPictures","duration":145,"views":11203866},{"youtube_id":"pG_A-Jkg9LM","title":"Zwiastun #1 [napisy]","type":"trailer","language":"pl","region":"PL","is_official":true,"published_at":"2024-09-30T16:52:51.000Z","quality":1080,"channel_name":"20th Century Studios Polska","duration":115,"views":30903},{"youtube_id":"eywqV0QyxvQ","title":"\u7279\u5831\u6620\u50cf\uff08\u5b57\u5e55\u7248\uff09","type":"trailer","language":"ja","region":"JP","is_official":true,"published_at":"2024-09-24T00:01:44.000Z","quality":1080,"channel_name":"\u30b5\u30fc\u30c1\u30e9\u30a4\u30c8\u30fb\u30d4\u30af\u30c1\u30e3\u30fc\u30ba","duration":113,"views":44543},{"youtube_id":"UhDFtPRZGlk","title":"\u05d8\u05e8\u05d9\u05d9\u05dc\u05e8 \u05e8\u05e9\u05de\u05d9 \u05de\u05ea\u05d5\u05e8\u05d2\u05dd","type":"trailer","language":"he","region":"IL","is_official":false,"published_at":"2025-01-01T07:35:51.000Z","quality":1080,"channel_name":"Searchlight Pics Israel","duration":145,"views":65272},{"youtube_id":"-CLMKE_PfMQ","title":"18 de junio en Disney+","type":"teaser","language":"es","region":"ES","is_official":true,"published_at":"2025-06-12T15:02:45.000Z","quality":1080,"channel_name":"20th Century Studios Espa\u00f1a","duration":30,"views":687},{"youtube_id":"F5E1ReqMnlo","title":"Hard Rain Review","type":"teaser","language":"en","region":"US","is_official":true,"published_at":"2025-03-09T04:00:16.000Z","quality":1080,"channel_name":"20th Century Studios Singapore","duration":30,"views":9650},{"youtube_id":"rsOxcq2A83M","title":"Take the stage. Be the first to watch at home.","type":"teaser","language":"en","region":"US","is_official":true,"published_at":"2025-03-07T17:01:08.000Z","quality":1080,"channel_name":"SearchlightPictures","duration":26,"views":11695},{"youtube_id":"fbBH18J-of0","title":"Accolades","type":"teaser","language":"en","region":"US","is_official":true,"published_at":"2025-03-01T04:00:25.000Z","quality":1080,"channel_name":"20th Century Studios Singapore","duration":16,"views":7724},{"youtube_id":"rB5uWJYBwMc","title":"15\u79d2\u30b9\u30dd\u30c3\u30c8\uff1c\u30ec\u30d3\u30e5\u30fc\u7de8\uff1e","type":"teaser","language":"ja","region":"JP","is_official":true,"published_at":"2025-02-28T16:32:05.000Z","quality":1080,"channel_name":"\u30b5\u30fc\u30c1\u30e9\u30a4\u30c8\u30fb\u30d4\u30af\u30c1\u30e3\u30fc\u30ba","duration":16,"views":134051},{"youtube_id":"sJHKHzSnxxw","title":"15\u79d2\u30b9\u30dd\u30c3\u30c8\uff1c\u30a2\u30ab\u30c7\u30df\u30fc\u8cde\u00ae\u30ce\u30df\u30cd\u30fc\u30c8\u7de8\uff1e","type":"teaser","language":"ja","region":"JP","is_official":true,"published_at":"2025-02-28T16:31:46.000Z","quality":1080,"channel_name":"\u30b5\u30fc\u30c1\u30e9\u30a4\u30c8\u30fb\u30d4\u30af\u30c1\u30e3\u30fc\u30ba","duration":16,"views":145271},{"youtube_id":"pmz1HymVMB8","title":"30\u79d2\u30b9\u30dd\u30c3\u30c8\uff1cGLIMPS H\u7de8\uff1e","type":"teaser","language":"ja","region":"JP","is_official":true,"published_at":"2025-02-28T16:31:17.000Z","quality":1080,"channel_name":"\u30b5\u30fc\u30c1\u30e9\u30a4\u30c8\u30fb\u30d4\u30af\u30c1\u30e3\u30fc\u30ba","duration":32,"views":8479},{"youtube_id":"NPcuIK2R3b4","title":"30\u79d2\u30b9\u30dd\u30c3\u30c8\uff1cICON\u7de8\uff1e","type":"teaser","language":"ja","region":"JP","is_official":true,"published_at":"2025-02-28T16:30:58.000Z","quality":1080,"channel_name":"\u30b5\u30fc\u30c1\u30e9\u30a4\u30c8\u30fb\u30d4\u30af\u30c1\u30e3\u30fc\u30ba","duration":31,"views":10456},{"youtube_id":"2T7oAa1lyuY","title":"Attention Review","type":"teaser","language":"en","region":"US","is_official":true,"published_at":"2025-02-27T04:00:02.000Z","quality":1080,"channel_name":"20th Century Studios Singapore","duration":30,"views":393261},{"youtube_id":"CVdbRstHgk4","title":"Anuncio: 'Rebosa talento'","type":"teaser","language":"es","region":"ES","is_official":true,"published_at":"2025-02-26T17:11:45.000Z","quality":1080,"channel_name":"20th Century Studios Espa\u00f1a","duration":30,"views":321365},{"youtube_id":"aHrirfYZ-kE","title":"Anuncio: 'UNO, DOS, TRES...'","type":"teaser","language":"es","region":"ES","is_official":true,"published_at":"2025-02-26T17:10:18.000Z","quality":1080,"channel_name":"20th Century Studios Espa\u00f1a","duration":30,"views":119379},{"youtube_id":"_fejyb0cxSA","title":"Be the first to watch. Buy it now only on Digital.","type":"teaser","language":"en","region":"US","is_official":true,"published_at":"2025-02-25T17:00:49.000Z","quality":1080,"channel_name":"SearchlightPictures","duration":23,"views":9334},{"youtube_id":"PUt7I2dTCbE","title":"Anuncio: 'Bonneville T100'","type":"teaser","language":"es","region":"ES","is_official":true,"published_at":"2025-02-18T10:48:09.000Z","quality":1080,"channel_name":"20th Century Studios Espa\u00f1a","duration":78,"views":1413},{"youtube_id":"rsDFi_jEhdQ","title":"Think Twice","type":"teaser","language":"en","region":"US","is_official":true,"published_at":"2025-02-13T20:00:37.000Z","quality":1080,"channel_name":"SearchlightPictures","duration":28,"views":275468},{"youtube_id":"prZ21e5I5zM","title":"Edward Norton","type":"teaser","language":"en","region":"US","is_official":true,"published_at":"2025-02-11T19:00:37.000Z","quality":1080,"channel_name":"SearchlightPictures","duration":30,"views":74291},{"youtube_id":"ZWYTXUUzeEA","title":"Rolling","type":"teaser","language":"en","region":"US","is_official":true,"published_at":"2025-02-10T18:14:56.000Z","quality":1080,"channel_name":"SearchlightPictures","duration":21,"views":49315},{"youtube_id":"HZtMWnprBuw","title":"Original","type":"teaser","language":"en","region":"US","is_official":true,"published_at":"2025-02-09T18:00:17.000Z","quality":1080,"channel_name":"SearchlightPictures","duration":29,"views":77048},{"youtube_id":"r2bo95ADB8c","title":"Revelation","type":"teaser","language":"en","region":"US","is_official":true,"published_at":"2025-02-08T18:00:38.000Z","quality":1080,"channel_name":"SearchlightPictures","duration":24,"views":25677},{"youtube_id":"PAkZXMn5ESk","title":"Triumph","type":"teaser","language":"en","region":"US","is_official":true,"published_at":"2025-02-07T19:00:27.000Z","quality":1080,"channel_name":"SearchlightPictures","duration":33,"views":44373},{"youtube_id":"jS1C5ccZmLY","title":"30\u79d2\u30b9\u30dd\u30c3\u30c8\uff1cGLIMPS\u7de8\uff1e","type":"teaser","language":"ja","region":"JP","is_official":true,"published_at":"2025-02-07T12:13:15.000Z","quality":1080,"channel_name":"\u30b5\u30fc\u30c1\u30e9\u30a4\u30c8\u30fb\u30d4\u30af\u30c1\u30e3\u30fc\u30ba","duration":32,"views":26545},{"youtube_id":"7oRn9YAnQLQ","title":"30\u79d2\u30b9\u30dd\u30c3\u30c8\uff1cICON \u7de8\uff1e","type":"teaser","language":"ja","region":"JP","is_official":true,"published_at":"2025-02-07T12:12:29.000Z","quality":1080,"channel_name":"\u30b5\u30fc\u30c1\u30e9\u30a4\u30c8\u30fb\u30d4\u30af\u30c1\u30e3\u30fc\u30ba","duration":31,"views":30882},{"youtube_id":"z4Ybcyzk_yw","title":"15\u79d2\u30b9\u30dd\u30c3\u30c8\uff1c\u30ec\u30d3\u30e5\u30fc\u7de8\uff1e","type":"teaser","language":"ja","region":"JP","is_official":true,"published_at":"2025-02-07T12:11:48.000Z","quality":1080,"channel_name":"\u30b5\u30fc\u30c1\u30e9\u30a4\u30c8\u30fb\u30d4\u30af\u30c1\u30e3\u30fc\u30ba","duration":16,"views":256805},{"youtube_id":"WEHOZvIqmjo","title":"15\u79d2\u30b9\u30dd\u30c3\u30c8\uff1c\u30a2\u30ab\u30c7\u30df\u30fc\u8cde\u00ae\u30ce\u30df\u30cd\u30fc\u30c8\u7de8\uff1e","type":"teaser","language":"ja","region":"JP","is_official":true,"published_at":"2025-02-07T12:11:09.000Z","quality":1080,"channel_name":"\u30b5\u30fc\u30c1\u30e9\u30a4\u30c8\u30fb\u30d4\u30af\u30c1\u30e3\u30fc\u30ba","duration":16,"views":497322},{"youtube_id":"uw_FeIp0OHs","title":"Remember Me","type":"teaser","language":"en","region":"US","is_official":true,"published_at":"2025-02-06T18:00:49.000Z","quality":1080,"channel_name":"SearchlightPictures","duration":31,"views":74256},{"youtube_id":"WIbjQ2q_6g0","title":"Anuncio: 'El reparto es espectacular'","type":"teaser","language":"es","region":"ES","is_official":true,"published_at":"2025-02-05T15:18:24.000Z","quality":1080,"channel_name":"20th Century Studios Espa\u00f1a","duration":30,"views":49309},{"youtube_id":"XE6QcFNZtsk","title":"Nominated for 8 Academy Awards\u00ae including Best Picture.","type":"teaser","language":"en","region":"US","is_official":true,"published_at":"2025-02-04T23:47:59.000Z","quality":1080,"channel_name":"SearchlightPictures","duration":31,"views":4397},{"youtube_id":"VjyKGWL1smk","title":"Fashion","type":"teaser","language":"en","region":"US","is_official":true,"published_at":"2025-02-02T17:00:34.000Z","quality":1080,"channel_name":"SearchlightPictures","duration":25,"views":7292},{"youtube_id":"lgnid6ASPso","title":"Accolades","type":"teaser","language":"en","region":"US","is_official":true,"published_at":"2025-01-29T17:00:54.000Z","quality":1080,"channel_name":"SearchlightPictures","duration":16,"views":2943},{"youtube_id":"fqVlDg6Sfjc","title":"Warm Welcome","type":"teaser","language":"en","region":"US","is_official":true,"published_at":"2025-01-28T17:00:45.000Z","quality":1080,"channel_name":"SearchlightPictures","duration":22,"views":7060},{"youtube_id":"9edO2LzpTqs","title":"Nominations","type":"teaser","language":"en","region":"US","is_official":true,"published_at":"2025-01-24T22:30:00.000Z","quality":1080,"channel_name":"SearchlightPictures","duration":16,"views":4887},{"youtube_id":"qUUcWwtQQVA","title":"The Times They Are A-Changin\u2019","type":"teaser","language":"en","region":"US","is_official":true,"published_at":"2025-01-24T17:00:59.000Z","quality":1080,"channel_name":"SearchlightPictures","duration":57,"views":309862},{"youtube_id":"AYv3_C90hlo","title":"Eight Nominations","type":"teaser","language":"en","region":"US","is_official":true,"published_at":"2025-01-23T23:44:47.000Z","quality":1080,"channel_name":"SearchlightPictures","duration":31,"views":15893},{"youtube_id":"jI6bzpKHVMs","title":"Subterranean Homesick Reviews","type":"teaser","language":"en","region":"US","is_official":true,"published_at":"2025-01-22T19:00:26.000Z","quality":1080,"channel_name":"SearchlightPictures","duration":11,"views":4938},{"youtube_id":"tmhNhi1GuL8","title":"Sold Out","type":"teaser","language":"en","region":"US","is_official":true,"published_at":"2025-01-22T18:00:42.000Z","quality":1080,"channel_name":"SearchlightPictures","duration":31,"views":11047},{"youtube_id":"-7uxS3aFTqM","title":"SAG","type":"teaser","language":"en","region":"US","is_official":true,"published_at":"2025-01-17T18:00:18.000Z","quality":1080,"channel_name":"SearchlightPictures","duration":26,"views":11044},{"youtube_id":"6mwa_B7sePk","title":"Romance","type":"teaser","language":"en","region":"US","is_official":true,"published_at":"2025-01-17T17:00:08.000Z","quality":1080,"channel_name":"SearchlightPictures","duration":46,"views":180048},{"youtube_id":"yt_jLKMds90","title":"Rising Sun","type":"teaser","language":"en","region":"US","is_official":true,"published_at":"2025-01-16T17:01:13.000Z","quality":1080,"channel_name":"SearchlightPictures","duration":52,"views":35538},{"youtube_id":"uFhrJyLH5Bk","title":"Experience","type":"teaser","language":"en","region":"US","is_official":true,"published_at":"2025-01-07T20:00:22.000Z","quality":1080,"channel_name":"SearchlightPictures","duration":16,"views":5965},{"youtube_id":"8m2LsvyQYWk","title":"Fearless","type":"teaser","language":"en","region":"US","is_official":true,"published_at":"2025-01-05T17:07:39.000Z","quality":1080,"channel_name":"SearchlightPictures","duration":16,"views":9828},{"youtube_id":"zt7kdNm15zQ","title":"\ud2f0\uc800 \uc608\uace0\ud3b8","type":"teaser","language":"ko","region":"KR","is_official":true,"published_at":"2025-01-03T09:01:08.000Z","quality":1080,"channel_name":"20th Century Studios Korea","duration":123,"views":12516},{"youtube_id":"DuEam_Mwkps","title":"BOB!","type":"teaser","language":"en","region":"US","is_official":true,"published_at":"2025-01-01T17:00:12.000Z","quality":1080,"channel_name":"SearchlightPictures","duration":23,"views":11517},{"youtube_id":"zZlbuebomM4","title":"Celebration","type":"teaser","language":"en","region":"US","is_official":true,"published_at":"2024-12-29T17:06:21.000Z","quality":1080,"channel_name":"SearchlightPictures","duration":16,"views":23339},{"youtube_id":"j7lb8318GgA","title":"Timoth\u00e9e Is Bob","type":"teaser","language":"en","region":"US","is_official":true,"published_at":"2024-12-28T20:39:02.000Z","quality":1080,"channel_name":"SearchlightPictures","duration":37,"views":33308},{"youtube_id":"uLbtKkaD2ZM","title":"Spirit","type":"teaser","language":"en","region":"US","is_official":true,"published_at":"2024-12-27T20:10:07.000Z","quality":1080,"channel_name":"SearchlightPictures","duration":42,"views":14950},{"youtube_id":"kY-jOtJFhwI","title":"15\u79d2\u30b9\u30dd\u30c3\u30c8\uff1c\u30b4\u30fc\u30eb\u30c7\u30f3\u30b0\u30ed\u30fc\u30d6\u8cde\u00ae\u30ce\u30df\u30cd\u30fc\u30c8\uff1e","type":"teaser","language":"ja","region":"JP","is_official":true,"published_at":"2024-12-27T06:09:51.000Z","quality":1080,"channel_name":"\u30b5\u30fc\u30c1\u30e9\u30a4\u30c8\u30fb\u30d4\u30af\u30c1\u30e3\u30fc\u30ba","duration":16,"views":222399},{"youtube_id":"zuBrn8SZ914","title":"Complete","type":"teaser","language":"en","region":"US","is_official":true,"published_at":"2024-12-26T17:00:54.000Z","quality":1080,"channel_name":"SearchlightPictures","duration":28,"views":90646},{"youtube_id":"Qm74qw4qH40","title":"Now Playing","type":"teaser","language":"en","region":"US","is_official":true,"published_at":"2024-12-25T17:02:41.000Z","quality":1080,"channel_name":"SearchlightPictures","duration":24,"views":45382},{"youtube_id":"S9XcqoOKpAk","title":"My Type","type":"teaser","language":"en","region":"US","is_official":true,"published_at":"2024-12-24T19:59:41.000Z","quality":1080,"channel_name":"SearchlightPictures","duration":20,"views":38471},{"youtube_id":"9_Gx8x-rb8g","title":"American Icon","type":"teaser","language":"en","region":"US","is_official":true,"published_at":"2024-12-23T18:01:58.000Z","quality":1080,"channel_name":"SearchlightPictures","duration":60,"views":34083},{"youtube_id":"Cc5QoGKCkYo","title":"Accolades","type":"teaser","language":"en","region":"US","is_official":true,"published_at":"2024-12-22T17:01:50.000Z","quality":1080,"channel_name":"SearchlightPictures","duration":16,"views":5019},{"youtube_id":"eZt4NF-R83A","title":"Hold On","type":"teaser","language":"en","region":"US","is_official":true,"published_at":"2024-12-20T19:00:31.000Z","quality":1080,"channel_name":"SearchlightPictures","duration":27,"views":20671},{"youtube_id":"sN2R3-itbUg","title":"Bob Dylan","type":"teaser","language":"en","region":"US","is_official":true,"published_at":"2024-12-20T17:00:57.000Z","quality":1080,"channel_name":"SearchlightPictures","duration":19,"views":200792},{"youtube_id":"YucqjtNoVNI","title":"Attention","type":"teaser","language":"en","region":"US","is_official":true,"published_at":"2024-12-19T22:04:56.000Z","quality":1080,"channel_name":"SearchlightPictures","duration":31,"views":13295},{"youtube_id":"Crn438FuVp8","title":"Joan Baez","type":"teaser","language":"en","region":"US","is_official":true,"published_at":"2024-12-19T17:00:17.000Z","quality":1080,"channel_name":"SearchlightPictures","duration":27,"views":316060},{"youtube_id":"J2HPjWPi95E","title":"Sylvie Russo","type":"teaser","language":"en","region":"US","is_official":true,"published_at":"2024-12-18T17:00:29.000Z","quality":1080,"channel_name":"SearchlightPictures","duration":25,"views":70945},{"youtube_id":"gKQ8BF0udXM","title":"One Week","type":"teaser","language":"en","region":"US","is_official":true,"published_at":"2024-12-18T16:00:41.000Z","quality":1080,"channel_name":"SearchlightPictures","duration":11,"views":3036},{"youtube_id":"-AwSLSJIlTs","title":"Pete Seeger","type":"teaser","language":"en","region":"US","is_official":true,"published_at":"2024-12-17T19:01:51.000Z","quality":1080,"channel_name":"SearchlightPictures","duration":20,"views":166007},{"youtube_id":"3c4mdnRhT74","title":"Johnny Cash","type":"teaser","language":"en","region":"US","is_official":true,"published_at":"2024-12-16T22:55:40.000Z","quality":1080,"channel_name":"SearchlightPictures","duration":21,"views":516529},{"youtube_id":"eEd83XBd2ug","title":"Icon Review","type":"teaser","language":"en","region":"US","is_official":true,"published_at":"2024-12-15T17:09:38.000Z","quality":1080,"channel_name":"SearchlightPictures","duration":31,"views":8726},{"youtube_id":"8Wwdr56pFgw","title":"Take 1","type":"teaser","language":"en","region":"US","is_official":true,"published_at":"2024-12-13T23:03:52.000Z","quality":1080,"channel_name":"SearchlightPictures","duration":24,"views":4824},{"youtube_id":"zZwqHXT8tDA","title":"I'll Sing Louder","type":"teaser","language":"en","region":"US","is_official":true,"published_at":"2024-12-12T22:05:46.000Z","quality":1080,"channel_name":"SearchlightPictures","duration":23,"views":47236},{"youtube_id":"OyoYPUqikBg","title":"Date Night","type":"teaser","language":"en","region":"US","is_official":true,"published_at":"2024-12-10T22:05:02.000Z","quality":1080,"channel_name":"SearchlightPictures","duration":20,"views":9731},{"youtube_id":"xes-sIZc198","title":"Get Tickets Now","type":"teaser","language":"en","region":"US","is_official":true,"published_at":"2024-12-09T17:02:54.000Z","quality":1080,"channel_name":"SearchlightPictures","duration":23,"views":77271},{"youtube_id":"dlhNqg7H35k","title":"Hit Play","type":"teaser","language":"en","region":"US","is_official":true,"published_at":"2024-12-05T14:01:04.000Z","quality":1080,"channel_name":"SearchlightPictures","duration":32,"views":37852},{"youtube_id":"7qziOUa3Pmc","title":"Rebel","type":"teaser","language":"en","region":"US","is_official":true,"published_at":"2024-12-01T23:01:21.000Z","quality":1080,"channel_name":"SearchlightPictures","duration":31,"views":38792},{"youtube_id":"p3UER_QJjlA","title":"A Complete Unknown | Teaser Ufficiale | Dal 23 Gennaio al Cinema","type":"teaser","language":"it","region":"IT","is_official":true,"published_at":"2024-09-09T14:29:04.000Z","quality":1080,"channel_name":"Searchlight Pictures Italia","duration":115,"views":18463},{"youtube_id":"qmzrxusbI_Y","title":"Teaser oficial en espa\u00f1ol","type":"teaser","language":"es","region":"ES","is_official":true,"published_at":"2024-08-19T11:43:22.000Z","quality":1080,"channel_name":"20th Century Studios Espa\u00f1a","duration":113,"views":22727},{"youtube_id":"TcNNteP22gQ","title":"Official Teaser","type":"teaser","language":"en","region":"US","is_official":true,"published_at":"2024-07-24T13:03:50.000Z","quality":1080,"channel_name":"SearchlightPictures","duration":113,"views":4403910},{"youtube_id":"iUd_vPl3FoU","title":"\u05e1\u05e4\u05d5\u05d8 30 \u05e9\u05e0\u05d9\u05d5\u05ea","type":"teaser","language":"he","region":"IL","is_official":false,"published_at":"2025-01-29T08:07:03.000Z","quality":1080,"channel_name":"Searchlight Pics Israel","duration":30,"views":333303},{"youtube_id":"XOz9QQzK36U","title":"Bob Dylan Gets Advice from Johnny Cash","type":"clip","language":"en","region":"US","is_official":true,"published_at":"2025-05-13T22:00:41.000Z","quality":1080,"channel_name":"Hulu","duration":164,"views":210861},{"youtube_id":"037jPYCRmwE","title":"It Ain't Me Babe","type":"clip","language":"en","region":"US","is_official":true,"published_at":"2025-05-12T23:00:00.000Z","quality":1080,"channel_name":"Hulu","duration":249,"views":1997990},{"youtube_id":"oIjYIzwBuzk","title":"\u7121\u6599\u30d7\u30ec\u30d3\u30e5\u30fc\uff08\u5b57\u5e55\u7248\uff09","type":"clip","language":"ja","region":"JP","is_official":true,"published_at":"2025-04-29T01:08:04.000Z","quality":1080,"channel_name":"20\u4e16\u7d00\u30b9\u30bf\u30b8\u30aa \u516c\u5f0f\u30c1\u30e3\u30f3\u30cd\u30eb","duration":589,"views":3695},{"youtube_id":"mHRJ_E9kJPE","title":"Una charla entre Johnny Cash y Bob Dylan","type":"clip","language":"es","region":"ES","is_official":true,"published_at":"2025-03-04T11:00:59.000Z","quality":1080,"channel_name":"20th Century Studios Espa\u00f1a","duration":57,"views":3765},{"youtube_id":"LloVocAz4OU","title":"\"It Ain't Me, Babe\" Official Clip","type":"clip","language":"en","region":"US","is_official":true,"published_at":"2025-01-15T19:00:23.000Z","quality":1080,"channel_name":"SearchlightPictures","duration":89,"views":1386128},{"youtube_id":"OD4bzGiSCXw","title":"\u672c\u7de8\u6620\u50cf\uff1cOne of a Kind\uff1e\uff08\u5b57\u5e55\u7248\uff09","type":"clip","language":"ja","region":"JP","is_official":true,"published_at":"2024-12-27T06:01:31.000Z","quality":1080,"channel_name":"\u30b5\u30fc\u30c1\u30e9\u30a4\u30c8\u30fb\u30d4\u30af\u30c1\u30e3\u30fc\u30ba","duration":75,"views":10624},{"youtube_id":"TZKwcp3Eurg","title":"\"Left Town Already\" Official Clip","type":"clip","language":"en","region":"US","is_official":true,"published_at":"2024-12-12T20:08:37.000Z","quality":1080,"channel_name":"SearchlightPictures","duration":58,"views":284519},{"youtube_id":"xMWBF-od5fg","title":"\"One of a Kind\" Official Clip","type":"clip","language":"en","region":"US","is_official":true,"published_at":"2024-12-11T20:24:00.000Z","quality":1080,"channel_name":"SearchlightPictures","duration":75,"views":609160},{"youtube_id":"gsMWyESq6UI","title":"\u30c6\u30a3\u30e2\u30b7\u30fc\u30fb\u30b9\u30da\u30b7\u30e3\u30eb\u30a4\u30d9\u30f3\u30c8 in tokyo 30\u79d2\u30c0\u30a4\u30b8\u30a7\u30b9\u30c8\u6620\u50cf","type":"featurette","language":"ja","region":"JP","is_official":true,"published_at":"2025-03-06T07:47:11.000Z","quality":1080,"channel_name":"\u30b5\u30fc\u30c1\u30e9\u30a4\u30c8\u30fb\u30d4\u30af\u30c1\u30e3\u30fc\u30ba","duration":31,"views":595},{"youtube_id":"N_JkBv_2VT8","title":"\u30c6\u30a3\u30e2\u30b7\u30fc\u30fb\u30b9\u30da\u30b7\u30e3\u30eb\u30a4\u30d9\u30f3\u30c8 in tokyo 60\u79d2\u30c0\u30a4\u30b8\u30a7\u30b9\u30c8\u6620\u50cf","type":"featurette","language":"ja","region":"JP","is_official":true,"published_at":"2025-03-01T06:20:12.000Z","quality":1080,"channel_name":"\u30b5\u30fc\u30c1\u30e9\u30a4\u30c8\u30fb\u30d4\u30af\u30c1\u30e3\u30fc\u30ba","duration":61,"views":2933},{"youtube_id":"Ztz2x9GPg1E","title":"\u30c6\u30a3\u30e2\u30b7\u30fc\u30fb\u30b7\u30e3\u30e9\u30e1\uff06\u30a8\u30eb\u30fb\u30d5\u30a1\u30cb\u30f3\u30b0\uff06\u30e2\u30cb\u30ab\u30fb\u30d0\u30eb\u30d0\u30ed \u30a4\u30f3\u30bf\u30d3\u30e5\u30fc\u7279\u5225\u6620\u50cf\uff08\u5b57\u5e55\u7248\uff09","type":"featurette","language":"ja","region":"JP","is_official":true,"published_at":"2025-02-27T04:02:01.000Z","quality":1080,"channel_name":"\u30b5\u30fc\u30c1\u30e9\u30a4\u30c8\u30fb\u30d4\u30af\u30c1\u30e3\u30fc\u30ba","duration":385,"views":27528},{"youtube_id":"iFtTJcLyk0k","title":"Reacciones del Pase Especial en Madrid","type":"featurette","language":"es","region":"ES","is_official":true,"published_at":"2025-02-26T15:57:27.000Z","quality":1080,"channel_name":"20th Century Studios Espa\u00f1a","duration":49,"views":8871},{"youtube_id":"ak79JOpeYYI","title":"Pase especial en Madrid","type":"featurette","language":"es","region":"ES","is_official":true,"published_at":"2025-02-26T10:39:34.000Z","quality":1080,"channel_name":"20th Century Studios Espa\u00f1a","duration":49,"views":11650},{"youtube_id":"PDKnfxRIkQ4","title":"\u7279\u5225\u6620\u50cf\uff1cFandango Exclusive Featurette\uff1e\uff08\u5b57\u5e55\u7248\uff09","type":"featurette","language":"ja","region":"JP","is_official":true,"published_at":"2025-02-19T04:14:42.000Z","quality":1080,"channel_name":"\u30b5\u30fc\u30c1\u30e9\u30a4\u30c8\u30fb\u30d4\u30af\u30c1\u30e3\u30fc\u30ba","duration":473,"views":108666},{"youtube_id":"GFICj73f8Hw","title":"Best Actor FYC","type":"featurette","language":"en","region":"US","is_official":true,"published_at":"2025-02-17T18:07:18.000Z","quality":1080,"channel_name":"SearchlightPictures","duration":31,"views":20239},{"youtube_id":"BjrWLoq7-6o","title":"I Was a Plate","type":"featurette","language":"en","region":"US","is_official":true,"published_at":"2025-02-16T17:00:13.000Z","quality":1080,"channel_name":"SearchlightPictures","duration":140,"views":14544},{"youtube_id":"bnWB_2gnepk","title":"It Ain\u2019t Easy","type":"featurette","language":"en","region":"US","is_official":true,"published_at":"2025-02-15T17:00:46.000Z","quality":1080,"channel_name":"SearchlightPictures","duration":90,"views":8124},{"youtube_id":"pLaCLBtSwXw","title":"James","type":"featurette","language":"en","region":"US","is_official":true,"published_at":"2025-02-05T20:17:50.000Z","quality":1080,"channel_name":"SearchlightPictures","duration":55,"views":8894},{"youtube_id":"C7rtx6cVYX0","title":"Finding the Voice","type":"featurette","language":"en","region":"US","is_official":true,"published_at":"2025-02-03T20:06:45.000Z","quality":1080,"channel_name":"SearchlightPictures","duration":52,"views":29321},{"youtube_id":"rwRGcjiqOvU","title":"\u30b8\u30a7\u30fc\u30e0\u30ba\u30fb\u30de\u30f3\u30b4\u30fc\u30eb\u30c9\u76e3\u7763\uff1c\u7b2c97\u56de\u30a2\u30ab\u30c7\u30df\u30fc\u8cde \u76e3\u7763\u8cde\u30ce\u30df\u30cd\u30fc\u30c8\uff1e\u30a4\u30f3\u30bf\u30d3\u30e5\u30fc \u7279\u5225\u6620\u50cf\uff08\u5b57\u5e55\u7248\uff09","type":"featurette","language":"ja","region":"JP","is_official":true,"published_at":"2025-02-03T06:02:46.000Z","quality":1080,"channel_name":"\u30b5\u30fc\u30c1\u30e9\u30a4\u30c8\u30fb\u30d4\u30af\u30c1\u30e3\u30fc\u30ba","duration":340,"views":2465},{"youtube_id":"kOUVCbIqOwY","title":"Boyd Holbrook as Johnny Cash","type":"featurette","language":"en","region":"US","is_official":true,"published_at":"2025-02-01T16:59:36.000Z","quality":1080,"channel_name":"SearchlightPictures","duration":41,"views":185235},{"youtube_id":"OptJoP6VKwc","title":"Elle Fanning as Sylvie Russo","type":"featurette","language":"en","region":"US","is_official":true,"published_at":"2025-01-31T18:00:18.000Z","quality":1080,"channel_name":"SearchlightPictures","duration":39,"views":64006},{"youtube_id":"EHL7OwCIC7A","title":"Monica Barbaro as Joan Baez","type":"featurette","language":"en","region":"US","is_official":true,"published_at":"2025-01-30T20:00:07.000Z","quality":1080,"channel_name":"SearchlightPictures","duration":45,"views":362626},{"youtube_id":"UQGeLTmshok","title":"Edward Norton as Pete Seeger","type":"featurette","language":"en","region":"US","is_official":true,"published_at":"2025-01-30T18:00:23.000Z","quality":1080,"channel_name":"SearchlightPictures","duration":38,"views":32343},{"youtube_id":"ruo-sGB0Ucc","title":"'A Complete Unknown' | Scene at The Academy","type":"featurette","language":"en","region":"US","is_official":true,"published_at":"2025-01-22T19:00:06.000Z","quality":1080,"channel_name":"Oscars","duration":568,"views":129201},{"youtube_id":"inSix8NuJkk","title":"\u201cBlowin\u2019 In the Wind\u201d Scene Breakdown","type":"featurette","language":"en","region":"US","is_official":true,"published_at":"2025-01-14T20:00:22.000Z","quality":1080,"channel_name":"SearchlightPictures","duration":58,"views":77507},{"youtube_id":"wJDXJKjLKoo","title":"Vocals","type":"featurette","language":"en","region":"US","is_official":true,"published_at":"2025-01-13T17:01:05.000Z","quality":1080,"channel_name":"SearchlightPictures","duration":41,"views":32862},{"youtube_id":"lmSlBTCX-h0","title":"Monica Barbaro","type":"featurette","language":"en","region":"US","is_official":true,"published_at":"2025-01-06T22:00:29.000Z","quality":1080,"channel_name":"SearchlightPictures","duration":40,"views":132447},{"youtube_id":"EfNcphjP9Lw","title":"Edward Norton","type":"featurette","language":"en","region":"US","is_official":true,"published_at":"2025-01-04T17:21:37.000Z","quality":1080,"channel_name":"SearchlightPictures","duration":43,"views":31053},{"youtube_id":"oek343EOr0g","title":"Alive","type":"featurette","language":"en","region":"US","is_official":true,"published_at":"2025-01-02T17:00:54.000Z","quality":1080,"channel_name":"SearchlightPictures","duration":31,"views":52591},{"youtube_id":"TaYqZeFedtQ","title":"Guess the Song","type":"featurette","language":"en","region":"US","is_official":true,"published_at":"2024-12-30T19:00:26.000Z","quality":1080,"channel_name":"SearchlightPictures","duration":39,"views":8877},{"youtube_id":"02d5J6KBiXc","title":"For The Fans","type":"featurette","language":"en","region":"US","is_official":true,"published_at":"2024-12-28T17:22:55.000Z","quality":1080,"channel_name":"SearchlightPictures","duration":33,"views":34318},{"youtube_id":"dsIkJsnOLbU","title":"Thanks Edward","type":"featurette","language":"en","region":"US","is_official":true,"published_at":"2024-12-27T23:00:25.000Z","quality":1080,"channel_name":"SearchlightPictures","duration":60,"views":13096},{"youtube_id":"0Ckp__XD1pM","title":"Locked In","type":"featurette","language":"en","region":"US","is_official":true,"published_at":"2024-12-26T23:00:00.000Z","quality":1080,"channel_name":"SearchlightPictures","duration":29,"views":3375},{"youtube_id":"90sNICRC2k4","title":"First Song","type":"featurette","language":"en","region":"US","is_official":true,"published_at":"2024-12-26T22:03:54.000Z","quality":1080,"channel_name":"SearchlightPictures","duration":44,"views":46233},{"youtube_id":"bKegHSyIM04","title":"Costumes","type":"featurette","language":"en","region":"US","is_official":true,"published_at":"2024-12-26T19:00:18.000Z","quality":1080,"channel_name":"SearchlightPictures","duration":49,"views":49193},{"youtube_id":"WyT9q8ONG4k","title":"The Gift of Bob Dylan","type":"featurette","language":"en","region":"US","is_official":true,"published_at":"2024-12-25T18:58:42.000Z","quality":1080,"channel_name":"SearchlightPictures","duration":17,"views":380325},{"youtube_id":"TpCTd1NoNgU","title":"Bob Dylan Walking Tour","type":"featurette","language":"en","region":"US","is_official":true,"published_at":"2024-12-23T23:54:30.000Z","quality":1080,"channel_name":"SearchlightPictures","duration":40,"views":8324},{"youtube_id":"yVpbicYblsA","title":"'A Complete Unknown' With Timoth\u00e9e Chalamet, Elle Fanning, And More | Academy Conversations","type":"featurette","language":"en","region":"US","is_official":true,"published_at":"2024-12-23T16:00:06.000Z","quality":1080,"channel_name":"Oscars","duration":805,"views":37806},{"youtube_id":"8I086lOUDIw","title":"Favorite Set Memories & Bob Dylan Songs","type":"featurette","language":"en","region":"US","is_official":true,"published_at":"2024-12-21T18:00:12.000Z","quality":1080,"channel_name":"SearchlightPictures","duration":57,"views":735867},{"youtube_id":"4jYZ-viLwkg","title":"Christmas","type":"featurette","language":"en","region":"US","is_official":true,"published_at":"2024-12-19T19:00:02.000Z","quality":1080,"channel_name":"SearchlightPictures","duration":25,"views":8300},{"youtube_id":"mKzdXCXSbsw","title":"Timoth\u00e9e Chalamet meets the winner of his Timoth\u00e9e Chalamet lookalike contest","type":"featurette","language":"en","region":"US","is_official":true,"published_at":"2024-12-15T02:51:35.000Z","quality":1080,"channel_name":"SearchlightPictures","duration":21,"views":28717},{"youtube_id":"oh7fapiHxOI","title":"NYC Premiere","type":"featurette","language":"en","region":"US","is_official":true,"published_at":"2024-12-14T23:12:42.000Z","quality":1080,"channel_name":"SearchlightPictures","duration":55,"views":3914},{"youtube_id":"xJk9ZWEJxyo","title":"World Premiere","type":"featurette","language":"en","region":"US","is_official":true,"published_at":"2024-12-12T19:03:04.000Z","quality":1080,"channel_name":"SearchlightPictures","duration":47,"views":3127},{"youtube_id":"pWP299eABos","title":"Atlanta","type":"featurette","language":"en","region":"US","is_official":true,"published_at":"2024-12-09T19:00:05.000Z","quality":1080,"channel_name":"SearchlightPictures","duration":30,"views":2080},{"youtube_id":"Y9DKNzpaJhI","title":"Church of Bob","type":"featurette","language":"en","region":"US","is_official":true,"published_at":"2024-12-08T17:00:28.000Z","quality":1080,"channel_name":"SearchlightPictures","duration":23,"views":5938},{"youtube_id":"3QRkaEQmJh0","title":"Superpowers","type":"featurette","language":"en","region":"US","is_official":true,"published_at":"2024-12-08T04:32:39.000Z","quality":1080,"channel_name":"SearchlightPictures","duration":23,"views":5842},{"youtube_id":"opKu1ZiN0-8","title":"Tour Day Two","type":"featurette","language":"en","region":"US","is_official":true,"published_at":"2024-12-08T03:58:10.000Z","quality":1080,"channel_name":"SearchlightPictures","duration":32,"views":2730},{"youtube_id":"NiRQvwgiTTg","title":"Tour Day 1","type":"featurette","language":"en","region":"US","is_official":true,"published_at":"2024-12-06T22:01:23.000Z","quality":1080,"channel_name":"SearchlightPictures","duration":36,"views":3656},{"youtube_id":"gbzj_Zc-fHw","title":"Mural","type":"featurette","language":"en","region":"US","is_official":true,"published_at":"2024-11-22T02:04:28.000Z","quality":1080,"channel_name":"SearchlightPictures","duration":17,"views":3533},{"youtube_id":"Sb7ThoUYxXE","title":"Detr\u00e1s de la historia [VOSE]","type":"behind_the_scenes","language":"es","region":"ES","is_official":true,"published_at":"2025-03-03T13:00:41.000Z","quality":1080,"channel_name":"20th Century Studios Espa\u00f1a","duration":168,"views":1520},{"youtube_id":"Q6x0d6Nzims","title":"\u7279\u5225\u6620\u50cf\uff1cLiveOnSet\uff1e\uff08\u5b57\u5e55\u7248\uff09","type":"behind_the_scenes","language":"ja","region":"JP","is_official":true,"published_at":"2025-02-13T03:22:51.000Z","quality":1080,"channel_name":"\u30b5\u30fc\u30c1\u30e9\u30a4\u30c8\u30fb\u30d4\u30af\u30c1\u30e3\u30fc\u30ba","duration":169,"views":39551},{"youtube_id":"dHiG1n6qOsU","title":"Sound Featurette","type":"behind_the_scenes","language":"en","region":"US","is_official":true,"published_at":"2025-02-11T21:52:47.000Z","quality":1080,"channel_name":"SearchlightPictures","duration":140,"views":20565},{"youtube_id":"FvlhoZglO9Q","title":"\u7279\u5225\u6620\u50cf\uff1cThe Ballad Of A True Original\uff1e\uff08\u5b57\u5e55\u7248\uff09","type":"behind_the_scenes","language":"ja","region":"JP","is_official":true,"published_at":"2025-01-30T03:03:28.000Z","quality":1080,"channel_name":"\u30b5\u30fc\u30c1\u30e9\u30a4\u30c8\u30fb\u30d4\u30af\u30c1\u30e3\u30fc\u30ba","duration":126,"views":17527},{"youtube_id":"ZimRyGLNv-8","title":"James Mangold","type":"behind_the_scenes","language":"en","region":"US","is_official":true,"published_at":"2025-01-21T17:00:42.000Z","quality":1080,"channel_name":"SearchlightPictures","duration":36,"views":6229},{"youtube_id":"6j2cytsIDcM","title":"Timoth\u00e9e Chalamet as Bob Dylan","type":"behind_the_scenes","language":"en","region":"US","is_official":true,"published_at":"2025-01-19T17:00:06.000Z","quality":1080,"channel_name":"SearchlightPictures","duration":38,"views":363766},{"youtube_id":"4EZgOS34UoU","title":"The Making-Of Broadcast Special","type":"behind_the_scenes","language":"en","region":"US","is_official":true,"published_at":"2025-01-10T17:45:13.000Z","quality":1080,"channel_name":"SearchlightPictures","duration":1334,"views":1458011},{"youtube_id":"9-F8wKM9Z18","title":"Chemistry","type":"behind_the_scenes","language":"en","region":"US","is_official":true,"published_at":"2024-12-31T20:00:04.000Z","quality":1080,"channel_name":"SearchlightPictures","duration":45,"views":15379},{"youtube_id":"TAy4J0dfIeQ","title":"A Complete Unknown | Featurette Live On Set","type":"behind_the_scenes","language":"it","region":"IT","is_official":true,"published_at":"2024-12-26T13:00:29.000Z","quality":1080,"channel_name":"Searchlight Pictures Italia","duration":170,"views":14080},{"youtube_id":"98k6G1TuNt4","title":"Rehearsals","type":"behind_the_scenes","language":"en","region":"US","is_official":true,"published_at":"2024-12-06T17:14:42.000Z","quality":1080,"channel_name":"SearchlightPictures","duration":49,"views":386787},{"youtube_id":"TvUW-ajrQ3s","title":"Featurette - Live on Set","type":"behind_the_scenes","language":"en","region":"US","is_official":true,"published_at":"2024-11-27T03:55:57.000Z","quality":1080,"channel_name":"SearchlightPictures","duration":168,"views":421860},{"youtube_id":"7f4DAFFx878","title":"A Complete Unknown | \"La Ballata di Una Vera Icona\" | Featurette","type":"behind_the_scenes","language":"it","region":"IT","is_official":true,"published_at":"2024-10-28T17:00:07.000Z","quality":1080,"channel_name":"Searchlight Pictures Italia","duration":126,"views":613},{"youtube_id":"5zC-wKO8y1k","title":"The Ballad of a True Original Featurette","type":"behind_the_scenes","language":"en","region":"US","is_official":true,"published_at":"2024-10-24T14:59:25.000Z","quality":1080,"channel_name":"SearchlightPictures","duration":125,"views":904758}],"trailer_groups":[{"group_id":824859,"type":"behind_the_scenes","title":"The Ballad of a True Original Featurette","languages":{"en":{"youtube_id":"5zC-wKO8y1k","title":"The Ballad of a True Original Featurette"}}},{"group_id":824860,"type":"behind_the_scenes","title":"A Complete Unknown | \"La Ballata di Una Vera Icona\" | Featurette","languages":{"it":{"youtube_id":"7f4DAFFx878","title":"A Complete Unknown | \"La Ballata di Una Vera Icona\" | Featurette"}}},{"group_id":824861,"type":"behind_the_scenes","title":"Featurette - Live on Set","languages":{"en":{"youtube_id":"TvUW-ajrQ3s","title":"Featurette - Live on Set"}}},{"group_id":824862,"type":"behind_the_scenes","title":"Rehearsals","languages":{"en":{"youtube_id":"98k6G1TuNt4","title":"Rehearsals"}}},{"group_id":824863,"type":"behind_the_scenes","title":"A Complete Unknown | Featurette Live On Set","languages":{"it":{"youtube_id":"TAy4J0dfIeQ","title":"A Complete Unknown | Featurette Live On Set"}}},{"group_id":824864,"type":"behind_the_scenes","title":"Chemistry","languages":{"en":{"youtube_id":"9-F8wKM9Z18","title":"Chemistry"}}},{"group_id":824865,"type":"behind_the_scenes","title":"The Making-Of Broadcast Special","languages":{"en":{"youtube_id":"4EZgOS34UoU","title":"The Making-Of Broadcast Special"}}},{"group_id":824866,"type":"behind_the_scenes","title":"Timoth\u00e9e Chalamet as Bob Dylan","languages":{"en":{"youtube_id":"6j2cytsIDcM","title":"Timoth\u00e9e Chalamet as Bob Dylan"}}},{"group_id":824867,"type":"behind_the_scenes","title":"James Mangold","languages":{"en":{"youtube_id":"ZimRyGLNv-8","title":"James Mangold"}}},{"group_id":824868,"type":"behind_the_scenes","title":"\u7279\u5225\u6620\u50cf\uff1cThe Ballad Of A True Original\uff1e\uff08\u5b57\u5e55\u7248\uff09","languages":{"ja":{"youtube_id":"FvlhoZglO9Q","title":"\u7279\u5225\u6620\u50cf\uff1cThe Ballad Of A True Original\uff1e\uff08\u5b57\u5e55\u7248\uff09"}}},{"group_id":824869,"type":"behind_the_scenes","title":"Sound Featurette","languages":{"en":{"youtube_id":"dHiG1n6qOsU","title":"Sound Featurette"}}},{"group_id":824870,"type":"behind_the_scenes","title":"\u7279\u5225\u6620\u50cf\uff1cLiveOnSet\uff1e\uff08\u5b57\u5e55\u7248\uff09","languages":{"ja":{"youtube_id":"Q6x0d6Nzims","title":"\u7279\u5225\u6620\u50cf\uff1cLiveOnSet\uff1e\uff08\u5b57\u5e55\u7248\uff09"}}},{"group_id":824871,"type":"behind_the_scenes","title":"Detr\u00e1s de la historia [VOSE]","languages":{"es":{"youtube_id":"Sb7ThoUYxXE","title":"Detr\u00e1s de la historia [VOSE]"}}},{"group_id":824872,"type":"clip","title":"\"One of a Kind\" Official Clip","languages":{"en":{"youtube_id":"xMWBF-od5fg","title":"\"One of a Kind\" Official Clip"}}},{"group_id":824873,"type":"clip","title":"\"Left Town Already\" Official Clip","languages":{"en":{"youtube_id":"TZKwcp3Eurg","title":"\"Left Town Already\" Official Clip"}}},{"group_id":824874,"type":"clip","title":"\u672c\u7de8\u6620\u50cf\uff1cOne of a Kind\uff1e\uff08\u5b57\u5e55\u7248\uff09","languages":{"ja":{"youtube_id":"OD4bzGiSCXw","title":"\u672c\u7de8\u6620\u50cf\uff1cOne of a Kind\uff1e\uff08\u5b57\u5e55\u7248\uff09"}}},{"group_id":824875,"type":"clip","title":"\"It Ain't Me, Babe\" Official Clip","languages":{"en":{"youtube_id":"LloVocAz4OU","title":"\"It Ain't Me, Babe\" Official Clip"}}},{"group_id":824876,"type":"clip","title":"Una charla entre Johnny Cash y Bob Dylan","languages":{"es":{"youtube_id":"mHRJ_E9kJPE","title":"Una charla entre Johnny Cash y Bob Dylan"}}},{"group_id":824877,"type":"clip","title":"\u7121\u6599\u30d7\u30ec\u30d3\u30e5\u30fc\uff08\u5b57\u5e55\u7248\uff09","languages":{"ja":{"youtube_id":"oIjYIzwBuzk","title":"\u7121\u6599\u30d7\u30ec\u30d3\u30e5\u30fc\uff08\u5b57\u5e55\u7248\uff09"}}},{"group_id":824878,"type":"clip","title":"It Ain't Me Babe","languages":{"en":{"youtube_id":"037jPYCRmwE","title":"It Ain't Me Babe"}}},{"group_id":824879,"type":"clip","title":"Bob Dylan Gets Advice from Johnny Cash","languages":{"en":{"youtube_id":"XOz9QQzK36U","title":"Bob Dylan Gets Advice from Johnny Cash"}}},{"group_id":824880,"type":"featurette","title":"Mural","languages":{"en":{"youtube_id":"gbzj_Zc-fHw","title":"Mural"}}},{"group_id":824881,"type":"featurette","title":"Tour Day 1","languages":{"en":{"youtube_id":"NiRQvwgiTTg","title":"Tour Day 1"}}},{"group_id":824882,"type":"featurette","title":"Tour Day Two","languages":{"en":{"youtube_id":"opKu1ZiN0-8","title":"Tour Day Two"}}},{"group_id":824883,"type":"featurette","title":"Superpowers","languages":{"en":{"youtube_id":"3QRkaEQmJh0","title":"Superpowers"}}},{"group_id":824884,"type":"featurette","title":"Church of Bob","languages":{"en":{"youtube_id":"Y9DKNzpaJhI","title":"Church of Bob"}}},{"group_id":824885,"type":"featurette","title":"Atlanta","languages":{"en":{"youtube_id":"pWP299eABos","title":"Atlanta"}}},{"group_id":824886,"type":"featurette","title":"World Premiere","languages":{"en":{"youtube_id":"xJk9ZWEJxyo","title":"World Premiere"}}},{"group_id":824887,"type":"featurette","title":"NYC Premiere","languages":{"en":{"youtube_id":"oh7fapiHxOI","title":"NYC Premiere"}}},{"group_id":824888,"type":"featurette","title":"Timoth\u00e9e Chalamet meets the winner of his Timoth\u00e9e Chalamet lookalike contest","languages":{"en":{"youtube_id":"mKzdXCXSbsw","title":"Timoth\u00e9e Chalamet meets the winner of his Timoth\u00e9e Chalamet lookalike contest"}}},{"group_id":824889,"type":"featurette","title":"Christmas","languages":{"en":{"youtube_id":"4jYZ-viLwkg","title":"Christmas"}}},{"group_id":824890,"type":"featurette","title":"Favorite Set Memories & Bob Dylan Songs","languages":{"en":{"youtube_id":"8I086lOUDIw","title":"Favorite Set Memories & Bob Dylan Songs"}}},{"group_id":824891,"type":"featurette","title":"'A Complete Unknown' With Timoth\u00e9e Chalamet, Elle Fanning, And More | Academy Conversations","languages":{"en":{"youtube_id":"yVpbicYblsA","title":"'A Complete Unknown' With Timoth\u00e9e Chalamet, Elle Fanning, And More | Academy Conversations"}}},{"group_id":824892,"type":"featurette","title":"Bob Dylan Walking Tour","languages":{"en":{"youtube_id":"TpCTd1NoNgU","title":"Bob Dylan Walking Tour"}}},{"group_id":824893,"type":"featurette","title":"The Gift of Bob Dylan","languages":{"en":{"youtube_id":"WyT9q8ONG4k","title":"The Gift of Bob Dylan"}}},{"group_id":824894,"type":"featurette","title":"Costumes","languages":{"en":{"youtube_id":"bKegHSyIM04","title":"Costumes"}}},{"group_id":824895,"type":"featurette","title":"First Song","languages":{"en":{"youtube_id":"90sNICRC2k4","title":"First Song"}}},{"group_id":824896,"type":"featurette","title":"Locked In","languages":{"en":{"youtube_id":"0Ckp__XD1pM","title":"Locked In"}}},{"group_id":824897,"type":"featurette","title":"Thanks Edward","languages":{"en":{"youtube_id":"dsIkJsnOLbU","title":"Thanks Edward"}}},{"group_id":824898,"type":"featurette","title":"For The Fans","languages":{"en":{"youtube_id":"02d5J6KBiXc","title":"For The Fans"}}},{"group_id":824899,"type":"featurette","title":"Guess the Song","languages":{"en":{"youtube_id":"TaYqZeFedtQ","title":"Guess the Song"}}},{"group_id":824900,"type":"featurette","title":"Alive","languages":{"en":{"youtube_id":"oek343EOr0g","title":"Alive"}}},{"group_id":824901,"type":"featurette","title":"Edward Norton","languages":{"en":{"youtube_id":"EfNcphjP9Lw","title":"Edward Norton"}}},{"group_id":824902,"type":"featurette","title":"Monica Barbaro","languages":{"en":{"youtube_id":"lmSlBTCX-h0","title":"Monica Barbaro"}}},{"group_id":824903,"type":"featurette","title":"Vocals","languages":{"en":{"youtube_id":"wJDXJKjLKoo","title":"Vocals"}}},{"group_id":824904,"type":"featurette","title":"\u201cBlowin\u2019 In the Wind\u201d Scene Breakdown","languages":{"en":{"youtube_id":"inSix8NuJkk","title":"\u201cBlowin\u2019 In the Wind\u201d Scene Breakdown"}}},{"group_id":824905,"type":"featurette","title":"'A Complete Unknown' | Scene at The Academy","languages":{"en":{"youtube_id":"ruo-sGB0Ucc","title":"'A Complete Unknown' | Scene at The Academy"}}},{"group_id":824906,"type":"featurette","title":"Edward Norton as Pete Seeger","languages":{"en":{"youtube_id":"UQGeLTmshok","title":"Edward Norton as Pete Seeger"}}},{"group_id":824907,"type":"featurette","title":"Monica Barbaro as Joan Baez","languages":{"en":{"youtube_id":"EHL7OwCIC7A","title":"Monica Barbaro as Joan Baez"}}},{"group_id":824908,"type":"featurette","title":"Elle Fanning as Sylvie Russo","languages":{"en":{"youtube_id":"OptJoP6VKwc","title":"Elle Fanning as Sylvie Russo"}}},{"group_id":824909,"type":"featurette","title":"Boyd Holbrook as Johnny Cash","languages":{"en":{"youtube_id":"kOUVCbIqOwY","title":"Boyd Holbrook as Johnny Cash"}}},{"group_id":824910,"type":"featurette","title":"\u30b8\u30a7\u30fc\u30e0\u30ba\u30fb\u30de\u30f3\u30b4\u30fc\u30eb\u30c9\u76e3\u7763\uff1c\u7b2c97\u56de\u30a2\u30ab\u30c7\u30df\u30fc\u8cde \u76e3\u7763\u8cde\u30ce\u30df\u30cd\u30fc\u30c8\uff1e\u30a4\u30f3\u30bf\u30d3\u30e5\u30fc \u7279\u5225\u6620\u50cf\uff08\u5b57\u5e55\u7248\uff09","languages":{"ja":{"youtube_id":"rwRGcjiqOvU","title":"\u30b8\u30a7\u30fc\u30e0\u30ba\u30fb\u30de\u30f3\u30b4\u30fc\u30eb\u30c9\u76e3\u7763\uff1c\u7b2c97\u56de\u30a2\u30ab\u30c7\u30df\u30fc\u8cde \u76e3\u7763\u8cde\u30ce\u30df\u30cd\u30fc\u30c8\uff1e\u30a4\u30f3\u30bf\u30d3\u30e5\u30fc \u7279\u5225\u6620\u50cf\uff08\u5b57\u5e55\u7248\uff09"}}},{"group_id":824911,"type":"featurette","title":"Finding the Voice","languages":{"en":{"youtube_id":"C7rtx6cVYX0","title":"Finding the Voice"}}},{"group_id":824912,"type":"featurette","title":"James","languages":{"en":{"youtube_id":"pLaCLBtSwXw","title":"James"}}},{"group_id":824913,"type":"featurette","title":"It Ain\u2019t Easy","languages":{"en":{"youtube_id":"bnWB_2gnepk","title":"It Ain\u2019t Easy"}}},{"group_id":824914,"type":"featurette","title":"I Was a Plate","languages":{"en":{"youtube_id":"BjrWLoq7-6o","title":"I Was a Plate"}}},{"group_id":824915,"type":"featurette","title":"Best Actor FYC","languages":{"en":{"youtube_id":"GFICj73f8Hw","title":"Best Actor FYC"}}},{"group_id":824916,"type":"featurette","title":"\u7279\u5225\u6620\u50cf\uff1cFandango Exclusive Featurette\uff1e\uff08\u5b57\u5e55\u7248\uff09","languages":{"ja":{"youtube_id":"PDKnfxRIkQ4","title":"\u7279\u5225\u6620\u50cf\uff1cFandango Exclusive Featurette\uff1e\uff08\u5b57\u5e55\u7248\uff09"}}},{"group_id":824917,"type":"featurette","title":"Pase especial en Madrid","languages":{"es":{"youtube_id":"ak79JOpeYYI","title":"Pase especial en Madrid"}}},{"group_id":824918,"type":"featurette","title":"Reacciones del Pase Especial en Madrid","languages":{"es":{"youtube_id":"iFtTJcLyk0k","title":"Reacciones del Pase Especial en Madrid"}}},{"group_id":824919,"type":"featurette","title":"\u30c6\u30a3\u30e2\u30b7\u30fc\u30fb\u30b7\u30e3\u30e9\u30e1\uff06\u30a8\u30eb\u30fb\u30d5\u30a1\u30cb\u30f3\u30b0\uff06\u30e2\u30cb\u30ab\u30fb\u30d0\u30eb\u30d0\u30ed \u30a4\u30f3\u30bf\u30d3\u30e5\u30fc\u7279\u5225\u6620\u50cf\uff08\u5b57\u5e55\u7248\uff09","languages":{"ja":{"youtube_id":"Ztz2x9GPg1E","title":"\u30c6\u30a3\u30e2\u30b7\u30fc\u30fb\u30b7\u30e3\u30e9\u30e1\uff06\u30a8\u30eb\u30fb\u30d5\u30a1\u30cb\u30f3\u30b0\uff06\u30e2\u30cb\u30ab\u30fb\u30d0\u30eb\u30d0\u30ed \u30a4\u30f3\u30bf\u30d3\u30e5\u30fc\u7279\u5225\u6620\u50cf\uff08\u5b57\u5e55\u7248\uff09"}}},{"group_id":824920,"type":"featurette","title":"\u30c6\u30a3\u30e2\u30b7\u30fc\u30fb\u30b9\u30da\u30b7\u30e3\u30eb\u30a4\u30d9\u30f3\u30c8 in tokyo 60\u79d2\u30c0\u30a4\u30b8\u30a7\u30b9\u30c8\u6620\u50cf","languages":{"ja":{"youtube_id":"N_JkBv_2VT8","title":"\u30c6\u30a3\u30e2\u30b7\u30fc\u30fb\u30b9\u30da\u30b7\u30e3\u30eb\u30a4\u30d9\u30f3\u30c8 in tokyo 60\u79d2\u30c0\u30a4\u30b8\u30a7\u30b9\u30c8\u6620\u50cf"}}},{"group_id":824921,"type":"featurette","title":"\u30c6\u30a3\u30e2\u30b7\u30fc\u30fb\u30b9\u30da\u30b7\u30e3\u30eb\u30a4\u30d9\u30f3\u30c8 in tokyo 30\u79d2\u30c0\u30a4\u30b8\u30a7\u30b9\u30c8\u6620\u50cf","languages":{"ja":{"youtube_id":"gsMWyESq6UI","title":"\u30c6\u30a3\u30e2\u30b7\u30fc\u30fb\u30b9\u30da\u30b7\u30e3\u30eb\u30a4\u30d9\u30f3\u30c8 in tokyo 30\u79d2\u30c0\u30a4\u30b8\u30a7\u30b9\u30c8\u6620\u50cf"}}},{"group_id":824922,"type":"teaser","title":"Official Teaser","languages":{"en":{"youtube_id":"TcNNteP22gQ","title":"Official Teaser"}}},{"group_id":824923,"type":"teaser","title":"Teaser oficial en espa\u00f1ol","languages":{"es":{"youtube_id":"qmzrxusbI_Y","title":"Teaser oficial en espa\u00f1ol"}}},{"group_id":824924,"type":"teaser","title":"A Complete Unknown | Teaser Ufficiale | Dal 23 Gennaio al Cinema","languages":{"it":{"youtube_id":"p3UER_QJjlA","title":"A Complete Unknown | Teaser Ufficiale | Dal 23 Gennaio al Cinema"}}},{"group_id":824925,"type":"teaser","title":"Rebel","languages":{"en":{"youtube_id":"7qziOUa3Pmc","title":"Rebel"}}},{"group_id":824926,"type":"teaser","title":"Hit Play","languages":{"en":{"youtube_id":"dlhNqg7H35k","title":"Hit Play"}}},{"group_id":824927,"type":"teaser","title":"Get Tickets Now","languages":{"en":{"youtube_id":"xes-sIZc198","title":"Get Tickets Now"}}},{"group_id":824928,"type":"teaser","title":"Date Night","languages":{"en":{"youtube_id":"OyoYPUqikBg","title":"Date Night"}}},{"group_id":824929,"type":"teaser","title":"I'll Sing Louder","languages":{"en":{"youtube_id":"zZwqHXT8tDA","title":"I'll Sing Louder"}}},{"group_id":824930,"type":"teaser","title":"Take 1","languages":{"en":{"youtube_id":"8Wwdr56pFgw","title":"Take 1"}}},{"group_id":824931,"type":"teaser","title":"Icon Review","languages":{"en":{"youtube_id":"eEd83XBd2ug","title":"Icon Review"}}},{"group_id":824932,"type":"teaser","title":"Johnny Cash","languages":{"en":{"youtube_id":"3c4mdnRhT74","title":"Johnny Cash"}}},{"group_id":824933,"type":"teaser","title":"Pete Seeger","languages":{"en":{"youtube_id":"-AwSLSJIlTs","title":"Pete Seeger"}}},{"group_id":824934,"type":"teaser","title":"One Week","languages":{"en":{"youtube_id":"gKQ8BF0udXM","title":"One Week"}}},{"group_id":824935,"type":"teaser","title":"Sylvie Russo","languages":{"en":{"youtube_id":"J2HPjWPi95E","title":"Sylvie Russo"}}},{"group_id":824936,"type":"teaser","title":"Joan Baez","languages":{"en":{"youtube_id":"Crn438FuVp8","title":"Joan Baez"}}},{"group_id":824937,"type":"teaser","title":"Attention","languages":{"en":{"youtube_id":"YucqjtNoVNI","title":"Attention"}}},{"group_id":824938,"type":"teaser","title":"Bob Dylan","languages":{"en":{"youtube_id":"sN2R3-itbUg","title":"Bob Dylan"}}},{"group_id":824939,"type":"teaser","title":"Hold On","languages":{"en":{"youtube_id":"eZt4NF-R83A","title":"Hold On"}}},{"group_id":824940,"type":"teaser","title":"Accolades","languages":{"en":{"youtube_id":"Cc5QoGKCkYo","title":"Accolades"}}},{"group_id":824941,"type":"teaser","title":"American Icon","languages":{"en":{"youtube_id":"9_Gx8x-rb8g","title":"American Icon"}}},{"group_id":824942,"type":"teaser","title":"My Type","languages":{"en":{"youtube_id":"S9XcqoOKpAk","title":"My Type"}}},{"group_id":824943,"type":"teaser","title":"Now Playing","languages":{"en":{"youtube_id":"Qm74qw4qH40","title":"Now Playing"}}},{"group_id":824944,"type":"teaser","title":"Complete","languages":{"en":{"youtube_id":"zuBrn8SZ914","title":"Complete"}}},{"group_id":824945,"type":"teaser","title":"Celebration","languages":{"en":{"youtube_id":"zZlbuebomM4","title":"Celebration"},"ja":{"youtube_id":"kY-jOtJFhwI","title":"15\u79d2\u30b9\u30dd\u30c3\u30c8\uff1c\u30b4\u30fc\u30eb\u30c7\u30f3\u30b0\u30ed\u30fc\u30d6\u8cde\u00ae\u30ce\u30df\u30cd\u30fc\u30c8\uff1e"}}},{"group_id":824946,"type":"teaser","title":"Spirit","languages":{"en":{"youtube_id":"uLbtKkaD2ZM","title":"Spirit"}}},{"group_id":824947,"type":"teaser","title":"Timoth\u00e9e Is Bob","languages":{"en":{"youtube_id":"j7lb8318GgA","title":"Timoth\u00e9e Is Bob"}}},{"group_id":824948,"type":"teaser","title":"BOB!","languages":{"en":{"youtube_id":"DuEam_Mwkps","title":"BOB!"}}},{"group_id":824949,"type":"teaser","title":"\ud2f0\uc800 \uc608\uace0\ud3b8","languages":{"ko":{"youtube_id":"zt7kdNm15zQ","title":"\ud2f0\uc800 \uc608\uace0\ud3b8"}}},{"group_id":824950,"type":"teaser","title":"Fearless","languages":{"en":{"youtube_id":"8m2LsvyQYWk","title":"Fearless"}}},{"group_id":824951,"type":"teaser","title":"Experience","languages":{"en":{"youtube_id":"uFhrJyLH5Bk","title":"Experience"}}},{"group_id":824952,"type":"teaser","title":"Rising Sun","languages":{"en":{"youtube_id":"yt_jLKMds90","title":"Rising Sun"}}},{"group_id":824953,"type":"teaser","title":"Romance","languages":{"en":{"youtube_id":"6mwa_B7sePk","title":"Romance"}}},{"group_id":824954,"type":"teaser","title":"SAG","languages":{"en":{"youtube_id":"-7uxS3aFTqM","title":"SAG"}}},{"group_id":824955,"type":"teaser","title":"Sold Out","languages":{"en":{"youtube_id":"tmhNhi1GuL8","title":"Sold Out"}}},{"group_id":824956,"type":"teaser","title":"Subterranean Homesick Reviews","languages":{"en":{"youtube_id":"jI6bzpKHVMs","title":"Subterranean Homesick Reviews"}}},{"group_id":824957,"type":"teaser","title":"Eight Nominations","languages":{"en":{"youtube_id":"AYv3_C90hlo","title":"Eight Nominations"}}},{"group_id":824958,"type":"teaser","title":"The Times They Are A-Changin\u2019","languages":{"en":{"youtube_id":"qUUcWwtQQVA","title":"The Times They Are A-Changin\u2019"}}},{"group_id":824959,"type":"teaser","title":"Nominations","languages":{"en":{"youtube_id":"9edO2LzpTqs","title":"Nominations"}}},{"group_id":824960,"type":"teaser","title":"Warm Welcome","languages":{"en":{"youtube_id":"fqVlDg6Sfjc","title":"Warm Welcome"}}},{"group_id":824961,"type":"teaser","title":"\u05e1\u05e4\u05d5\u05d8 30 \u05e9\u05e0\u05d9\u05d5\u05ea","languages":{"he":{"youtube_id":"iUd_vPl3FoU","title":"\u05e1\u05e4\u05d5\u05d8 30 \u05e9\u05e0\u05d9\u05d5\u05ea"}}},{"group_id":824962,"type":"teaser","title":"Accolades","languages":{"en":{"youtube_id":"lgnid6ASPso","title":"Accolades"}}},{"group_id":824963,"type":"teaser","title":"Fashion","languages":{"en":{"youtube_id":"VjyKGWL1smk","title":"Fashion"}}},{"group_id":824964,"type":"teaser","title":"Nominated for 8 Academy Awards\u00ae including Best Picture.","languages":{"en":{"youtube_id":"XE6QcFNZtsk","title":"Nominated for 8 Academy Awards\u00ae including Best Picture."},"es":{"youtube_id":"WIbjQ2q_6g0","title":"Anuncio: 'El reparto es espectacular'"}}},{"group_id":824965,"type":"teaser","title":"Remember Me","languages":{"en":{"youtube_id":"uw_FeIp0OHs","title":"Remember Me"},"ja":{"youtube_id":"7oRn9YAnQLQ","title":"30\u79d2\u30b9\u30dd\u30c3\u30c8\uff1cICON \u7de8\uff1e"}}},{"group_id":824966,"type":"teaser","title":"15\u79d2\u30b9\u30dd\u30c3\u30c8\uff1c\u30a2\u30ab\u30c7\u30df\u30fc\u8cde\u00ae\u30ce\u30df\u30cd\u30fc\u30c8\u7de8\uff1e","languages":{"ja":{"youtube_id":"WEHOZvIqmjo","title":"15\u79d2\u30b9\u30dd\u30c3\u30c8\uff1c\u30a2\u30ab\u30c7\u30df\u30fc\u8cde\u00ae\u30ce\u30df\u30cd\u30fc\u30c8\u7de8\uff1e"}}},{"group_id":824967,"type":"teaser","title":"15\u79d2\u30b9\u30dd\u30c3\u30c8\uff1c\u30ec\u30d3\u30e5\u30fc\u7de8\uff1e","languages":{"ja":{"youtube_id":"z4Ybcyzk_yw","title":"15\u79d2\u30b9\u30dd\u30c3\u30c8\uff1c\u30ec\u30d3\u30e5\u30fc\u7de8\uff1e"}}},{"group_id":824968,"type":"teaser","title":"Triumph","languages":{"en":{"youtube_id":"PAkZXMn5ESk","title":"Triumph"},"ja":{"youtube_id":"jS1C5ccZmLY","title":"30\u79d2\u30b9\u30dd\u30c3\u30c8\uff1cGLIMPS\u7de8\uff1e"}}},{"group_id":824969,"type":"teaser","title":"Revelation","languages":{"en":{"youtube_id":"r2bo95ADB8c","title":"Revelation"}}},{"group_id":824970,"type":"teaser","title":"Original","languages":{"en":{"youtube_id":"HZtMWnprBuw","title":"Original"}}},{"group_id":824971,"type":"teaser","title":"Rolling","languages":{"en":{"youtube_id":"ZWYTXUUzeEA","title":"Rolling"}}},{"group_id":824972,"type":"teaser","title":"Edward Norton","languages":{"en":{"youtube_id":"prZ21e5I5zM","title":"Edward Norton"}}},{"group_id":824973,"type":"teaser","title":"Think Twice","languages":{"en":{"youtube_id":"rsDFi_jEhdQ","title":"Think Twice"}}},{"group_id":824974,"type":"teaser","title":"Anuncio: 'Bonneville T100'","languages":{"es":{"youtube_id":"PUt7I2dTCbE","title":"Anuncio: 'Bonneville T100'"}}},{"group_id":824975,"type":"teaser","title":"Be the first to watch. Buy it now only on Digital.","languages":{"en":{"youtube_id":"_fejyb0cxSA","title":"Be the first to watch. Buy it now only on Digital."}}},{"group_id":824976,"type":"teaser","title":"Attention Review","languages":{"en":{"youtube_id":"2T7oAa1lyuY","title":"Attention Review"},"es":{"youtube_id":"aHrirfYZ-kE","title":"Anuncio: 'UNO, DOS, TRES...'"},"ja":{"youtube_id":"NPcuIK2R3b4","title":"30\u79d2\u30b9\u30dd\u30c3\u30c8\uff1cICON\u7de8\uff1e"}}},{"group_id":824977,"type":"teaser","title":"Anuncio: 'Rebosa talento'","languages":{"es":{"youtube_id":"CVdbRstHgk4","title":"Anuncio: 'Rebosa talento'"},"ja":{"youtube_id":"pmz1HymVMB8","title":"30\u79d2\u30b9\u30dd\u30c3\u30c8\uff1cGLIMPS H\u7de8\uff1e"}}},{"group_id":824978,"type":"teaser","title":"Accolades","languages":{"en":{"youtube_id":"fbBH18J-of0","title":"Accolades"},"ja":{"youtube_id":"sJHKHzSnxxw","title":"15\u79d2\u30b9\u30dd\u30c3\u30c8\uff1c\u30a2\u30ab\u30c7\u30df\u30fc\u8cde\u00ae\u30ce\u30df\u30cd\u30fc\u30c8\u7de8\uff1e"}}},{"group_id":824979,"type":"teaser","title":"15\u79d2\u30b9\u30dd\u30c3\u30c8\uff1c\u30ec\u30d3\u30e5\u30fc\u7de8\uff1e","languages":{"ja":{"youtube_id":"rB5uWJYBwMc","title":"15\u79d2\u30b9\u30dd\u30c3\u30c8\uff1c\u30ec\u30d3\u30e5\u30fc\u7de8\uff1e"}}},{"group_id":824980,"type":"teaser","title":"Take the stage. Be the first to watch at home.","languages":{"en":{"youtube_id":"rsOxcq2A83M","title":"Take the stage. Be the first to watch at home."}}},{"group_id":824981,"type":"teaser","title":"Hard Rain Review","languages":{"en":{"youtube_id":"F5E1ReqMnlo","title":"Hard Rain Review"}}},{"group_id":824982,"type":"teaser","title":"18 de junio en Disney+","languages":{"es":{"youtube_id":"-CLMKE_PfMQ","title":"18 de junio en Disney+"}}},{"group_id":824983,"type":"trailer","title":"\u7279\u5831\u6620\u50cf\uff08\u5b57\u5e55\u7248\uff09","languages":{"ja":{"youtube_id":"eywqV0QyxvQ","title":"\u7279\u5831\u6620\u50cf\uff08\u5b57\u5e55\u7248\uff09"}}},{"group_id":824984,"type":"trailer","title":"Zwiastun #1 [napisy]","languages":{"pl":{"youtube_id":"pG_A-Jkg9LM","title":"Zwiastun #1 [napisy]"}}},{"group_id":824985,"type":"trailer","title":"Official Trailer","languages":{"en":{"youtube_id":"FdV-Cs5o8mc","title":"Official Trailer"},"es":{"youtube_id":"5WGNuAR__NM","title":"Tr\u00e1iler oficial en espa\u00f1ol"},"sv":{"youtube_id":"lbwhookIZ2c","title":"A COMPLETE UNKNOWN l Trailer"},"fi":{"youtube_id":"8R7LCOLLZA0","title":"A COMPLETE UNKNOWN l Traileri"}}},{"group_id":824986,"type":"trailer","title":"Tr\u00e1iler Oficial [VOSE]","languages":{"es":{"youtube_id":"LmoNBGdeoyw","title":"Tr\u00e1iler Oficial [VOSE]"},"it":{"youtube_id":"pHvskfTszoU","title":"A Complete Unknown | Trailer Ufficiale"}}},{"group_id":824987,"type":"trailer","title":"\u4e88\u544a\u6620\u50cf\uff08\u5b57\u5e55\u7248\uff09","languages":{"fr":{"youtube_id":"Nb_Gvv52-EI","title":"UN PARFAIT INCONNU | Bande-annonce officielle | FR"},"de":{"youtube_id":"nyIknvGt8Lg","title":"Like A Complete Unknown I Offizieller Trailer I Ab 27. Februar nur im Kino"},"ja":{"youtube_id":"ilkdlJ_Nh0A","title":"\u4e88\u544a\u6620\u50cf\uff08\u5b57\u5e55\u7248\uff09"}}},{"group_id":824988,"type":"trailer","title":"Tam Bir Bilinmez | \u0130lk Fragman","languages":{"tr":{"youtube_id":"syxd43MuBC4","title":"Tam Bir Bilinmez | \u0130lk Fragman"}}},{"group_id":824989,"type":"trailer","title":"Final Trailer","languages":{"en":{"youtube_id":"NO9hXSD5K4A","title":"Final Trailer"}}},{"group_id":824990,"type":"trailer","title":"\u05d8\u05e8\u05d9\u05d9\u05dc\u05e8 \u05e8\u05e9\u05de\u05d9 \u05de\u05ea\u05d5\u05e8\u05d2\u05dd","languages":{"he":{"youtube_id":"UhDFtPRZGlk","title":"\u05d8\u05e8\u05d9\u05d9\u05dc\u05e8 \u05e8\u05e9\u05de\u05d9 \u05de\u05ea\u05d5\u05e8\u05d2\u05dd"}}},{"group_id":824991,"type":"trailer","title":"A Complete Unknown | Trailer Finale | Dal 23 Gennaio al Cinema","languages":{"it":{"youtube_id":"KuVnRN_LVOw","title":"A Complete Unknown | Trailer Finale | Dal 23 Gennaio al Cinema"}}},{"group_id":824992,"type":"trailer","title":"\uba54\uc778 \uc608\uace0\ud3b8","languages":{"ko":{"youtube_id":"NdQbdU7H8kg","title":"\uba54\uc778 \uc608\uace0\ud3b8"}}},{"group_id":824993,"type":"trailer","title":"Nuevo Tr\u00e1iler en espa\u00f1ol","languages":{"es":{"youtube_id":"YLYNZ4jDcdk","title":"Nuevo Tr\u00e1iler en espa\u00f1ol"}}},{"group_id":824994,"type":"trailer","title":"Be the first to watch at home, nominated for 8 Academy Awards\u00ae.","languages":{"en":{"youtube_id":"ob4SHtT6cC0","title":"Be the first to watch at home, nominated for 8 Academy Awards\u00ae."}}}]}