{"imdb_id":"tt1188677","tmdb_id":86674,"title":"Asyl: Park and Love Hotel","original_title":"\u30d1\u30fc\u30af \u30a2\u30f3\u30c9 \u30e9\u30d6\u30db\u30c6\u30eb","year":2007,"release_date":null,"imdb_rating":7.2,"imdb_votes":102,"runtime":111,"overview":"There is an old love hotel in Tokyo's Shinjuku district where couples can rent a room by the hour for romantic assignations. However, few of its regular customers seem to come there for sexual encounters; the hotel has become a hangout for rootless teenagers, senior citizens looking for a place to relax, and kids that play under the watchful eye of its owner...","poster_path":"/jCYSOVPaZIru5UpYH69M4gfuS9o.jpg","backdrop_path":"/835HYDEVagbpjk3m3rLVGLPnYbI.jpg","original_language":"ja","genres":["Drama","Romance"],"slug":"asyl-park-and-love-hotel-2007-tt1188677","trailers":[{"youtube_id":"YxTAHIJj5Cs","title":"\u7b2c17\u56dePFF\u30b9\u30ab\u30e9\u30b7\u30c3\u30d7\u4f5c\u54c1\u3000\u6620\u753b\u300e\u30d1\u30fc\u30af \u30a2\u30f3\u30c9 \u30e9\u30d6\u30db\u30c6\u30eb\u300f\u4e88\u544a\u7de8","type":"trailer","language":"ja","region":"JP","is_official":false,"published_at":"2011-08-31T15:05:08.000Z","quality":360,"channel_name":"\u3074\u3042\u30d5\u30a3\u30eb\u30e0\u30d5\u30a7\u30b9\u30c6\u30a3\u30d0\u30eb","duration":108,"views":3741}],"trailer_groups":[{"group_id":1014078,"type":"trailer","title":"\u7b2c17\u56dePFF\u30b9\u30ab\u30e9\u30b7\u30c3\u30d7\u4f5c\u54c1\u3000\u6620\u753b\u300e\u30d1\u30fc\u30af \u30a2\u30f3\u30c9 \u30e9\u30d6\u30db\u30c6\u30eb\u300f\u4e88\u544a\u7de8","languages":{"ja":{"youtube_id":"YxTAHIJj5Cs","title":"\u7b2c17\u56dePFF\u30b9\u30ab\u30e9\u30b7\u30c3\u30d7\u4f5c\u54c1\u3000\u6620\u753b\u300e\u30d1\u30fc\u30af \u30a2\u30f3\u30c9 \u30e9\u30d6\u30db\u30c6\u30eb\u300f\u4e88\u544a\u7de8"}}}]}