{"imdb_id":"tt2017486","tmdb_id":137347,"title":"Closer to the Moon","original_title":"Closer to the Moon","year":2014,"release_date":null,"imdb_rating":6.7,"imdb_votes":4464,"runtime":112,"overview":"A Romanian police officer teams up with a small crew of bank robbers to pull off a heist by convincing everyone at the scene of the crime that they are only filming a movie.","poster_path":"/pBqnSEkLMZoEFgOCQLxM7wKmmS0.jpg","backdrop_path":"/qaqV7EF3UOoJi3ai0iUiFiugnFJ.jpg","original_language":"en","genres":["Comedy","Drama"],"slug":"closer-to-the-moon-2014-tt2017486","trailers":[{"youtube_id":"_7tOgHYnvgE","title":"Official Trailer","type":"trailer","language":"en","region":"US","is_official":true,"published_at":"2015-04-09T00:03:36.000Z","quality":1080,"channel_name":"Independent Film Company","duration":150,"views":127131},{"youtube_id":"JR8uv9SClck","title":"\"GANG ROSENTHALA \" trailer - Official Selection of 12th WJFF 2014","type":"trailer","language":"pl","region":"PL","is_official":false,"published_at":"2014-10-17T08:54:09.000Z","quality":720,"channel_name":"Warsaw Jewish Film Festival","duration":129,"views":3614}],"trailer_groups":[{"group_id":915987,"type":"trailer","title":"\"GANG ROSENTHALA \" trailer - Official Selection of 12th WJFF 2014","languages":{"pl":{"youtube_id":"JR8uv9SClck","title":"\"GANG ROSENTHALA \" trailer - Official Selection of 12th WJFF 2014"}}},{"group_id":915988,"type":"trailer","title":"Official Trailer","languages":{"en":{"youtube_id":"_7tOgHYnvgE","title":"Official Trailer"}}}]}