{"imdb_id":"tt2308860","tmdb_id":133603,"title":"Traffickers","original_title":"\uacf5\ubaa8\uc790\ub4e4","year":2012,"release_date":null,"imdb_rating":6.3,"imdb_votes":928,"runtime":111,"overview":"A thriller about the passengers with different objectives on board a cruiser headed for China, being chased over and over again and unexpected happening of things.","poster_path":"/rjGOIyRk5T6gC3MM8NGUTYCAeU8.jpg","backdrop_path":"/tdCcYh2Km89L6kNvcFEBmq5Y2Do.jpg","original_language":"ko","genres":["Drama","Action","Thriller","Crime"],"slug":"traffickers-2012-tt2308860","trailers":[{"youtube_id":"HUQ_4LdCmzo","title":"Traffickers (2012)","type":"trailer","language":"en","region":"US","is_official":true,"published_at":"2014-09-11T04:43:01.000Z","quality":480,"channel_name":"KoreanFilmBiz KoBiz","duration":72,"views":19644}],"trailer_groups":[{"group_id":962366,"type":"trailer","title":"Traffickers (2012)","languages":{"en":{"youtube_id":"HUQ_4LdCmzo","title":"Traffickers (2012)"}}}]}