{"imdb_id":"tt28487871","tmdb_id":1171541,"title":"Sniper: G.R.I.T. - Global Response & Intelligence Team","original_title":"Sniper: G.R.I.T. - Global Response & Intelligence Team","year":2023,"release_date":null,"imdb_rating":5.0,"imdb_votes":2244,"runtime":92,"overview":"When an international terrorist cult threatens global political stability and kidnaps a fellow agent, Ace Sniper Brandon Beckett and the newly-formed Global Response & Intelligence Team \u2013 or G.R.I.T. \u2013 led by Colonel Stone must travel across the world to Malta, infiltrate the cult, and take out its leader to free Lady Death and stop the global threat.","poster_path":"/xpdM0RDM6lWgtLsYVb1XpYmNxzd.jpg","backdrop_path":"/qz8xWFW29f1t7eL15iOWWgzXyVo.jpg","original_language":"en","genres":["Action","Thriller"],"slug":"sniper-g-r-i-t-global-response-intelligence-team-2023-tt28487871","trailers":[{"youtube_id":"AAT4TCet1KQ","title":"Official Trailer","type":"trailer","language":"en","region":"US","is_official":true,"published_at":"2023-09-06T19:00:04.000Z","quality":1080,"channel_name":"Sony Pictures Entertainment","duration":104,"views":722581},{"youtube_id":"Y124ln05cq4","title":"SNIPER G.R.I.T. Bande Annonce VF (2023)","type":"trailer","language":"fr","region":"FR","is_official":false,"published_at":"2023-12-19T19:19:10.000Z","quality":1080,"channel_name":"AuCin\u00e9","duration":112,"views":6356},{"youtube_id":"Gxb5qOu68uU","title":"Offizieller Trailer","type":"trailer","language":"de","region":"DE","is_official":false,"published_at":"2023-11-23T07:32:31.000Z","quality":1080,"channel_name":"Sony Pics at Home DE","duration":96,"views":3269},{"youtube_id":"7k5isqe2ElE","title":"Official Film Clip","type":"clip","language":"en","region":"US","is_official":true,"published_at":"2023-10-22T22:00:08.000Z","quality":1080,"channel_name":"Sony Pictures Entertainment","duration":70,"views":54345},{"youtube_id":"3UgNRGsQeuc","title":"Extended Preview","type":"clip","language":"en","region":"US","is_official":true,"published_at":"2023-09-29T22:00:02.000Z","quality":1080,"channel_name":"Sony Pictures Entertainment","duration":568,"views":50533}],"trailer_groups":[{"group_id":935603,"type":"clip","title":"Extended Preview","languages":{"en":{"youtube_id":"3UgNRGsQeuc","title":"Extended Preview"}}},{"group_id":935604,"type":"clip","title":"Official Film Clip","languages":{"en":{"youtube_id":"7k5isqe2ElE","title":"Official Film Clip"}}},{"group_id":935605,"type":"trailer","title":"Official Trailer","languages":{"en":{"youtube_id":"AAT4TCet1KQ","title":"Official Trailer"}}},{"group_id":935606,"type":"trailer","title":"Offizieller Trailer","languages":{"de":{"youtube_id":"Gxb5qOu68uU","title":"Offizieller Trailer"}}},{"group_id":935607,"type":"trailer","title":"SNIPER G.R.I.T. Bande Annonce VF (2023)","languages":{"fr":{"youtube_id":"Y124ln05cq4","title":"SNIPER G.R.I.T. Bande Annonce VF (2023)"}}}]}