{"imdb_id":"tt4363254","tmdb_id":325416,"title":"The Boda Boda Thieves","original_title":"Abaabi da Boda Boda","year":2015,"release_date":null,"imdb_rating":6.9,"imdb_votes":29,"runtime":85,"overview":"Even though he is only 15 years old, when his father is injured in a road accident Abel takes up the responsibility of manning the family 'boda boda' to provide for the family. Abel however, is always on the lookout for a shortcut and when a local hustler offers him the chance of being a snatch and grab get-away driver, he lurches headlong into a world of easy money and quick thrills.","poster_path":"/9i2gfeCOMVpZGSa9IwZfkeycLVr.jpg","backdrop_path":null,"original_language":"en","genres":["Drama","Crime"],"slug":"the-boda-boda-thieves-2015-tt4363254","trailers":[{"youtube_id":"5fdGLTLPEJw","title":"THE BODA BODA THIEVES Trailer | English Subtitles","type":"trailer","language":"en","region":"US","is_official":false,"published_at":"2017-11-17T09:34:21.000Z","quality":720,"channel_name":"Rushlake Media GmbH","duration":136,"views":4055}],"trailer_groups":[{"group_id":1034025,"type":"trailer","title":"THE BODA BODA THIEVES Trailer | English Subtitles","languages":{"en":{"youtube_id":"5fdGLTLPEJw","title":"THE BODA BODA THIEVES Trailer | English Subtitles"}}}]}