{"imdb_id":"tt7896362","tmdb_id":623798,"title":"Kampai! Sake Sisters","original_title":"\u30ab\u30f3\u30d1\u30a4\uff01\u65e5\u672c\u9152\u306b\u604b\u3057\u305f\u5973\u305f\u3061","year":2019,"release_date":null,"imdb_rating":6.8,"imdb_votes":29,"runtime":96,"overview":"Sake is a traditional alcoholic beverage from Japan and is otherwise known as rice wine. Women were prohibited from entering the many large and small sake breweries dotting Japan for centuries. However, times have changed and women are present on the sake scene today. In several cases, they are integral to the Japanese brewery business. The documentary depicts women who are not only enthusiasts, but also leaving their marks on the evolution of this Japanese mainstay.","poster_path":"/1eKwGSbmbvvISABs9pByaSBW4jf.jpg","backdrop_path":"/r1MXX8WTvUppAD18VPyw7G3Ozrc.jpg","original_language":"ja","genres":["Documentary"],"slug":"kampai-sake-sisters-2019-tt7896362","trailers":[{"youtube_id":"67ZxzBtGapI","title":"\u300e\u30ab\u30f3\u30d1\u30a4\uff01\u65e5\u672c\u9152\u306b\u604b\u3057\u305f\u5973\u305f\u3061\u300f\u6d77\u5916\u7248\u4e88\u544a","type":"trailer","language":"ja","region":"JP","is_official":true,"published_at":"2021-01-12T01:57:08.000Z","quality":1080,"channel_name":"SYNCA Creations Inc.","duration":200,"views":374},{"youtube_id":"RLyoN5FNGNY","title":"\u6620\u753b\u300e\u30ab\u30f3\u30d1\u30a4\uff01\u65e5\u672c\u9152\u306b\u604b\u3057\u305f\u5973\u305f\u3061\u300f\u4e88\u544a","type":"trailer","language":"ja","region":"JP","is_official":true,"published_at":"2019-02-07T03:00:20.000Z","quality":1080,"channel_name":"SYNCA Creations Inc.","duration":117,"views":14954}],"trailer_groups":[{"group_id":1034100,"type":"trailer","title":"\u6620\u753b\u300e\u30ab\u30f3\u30d1\u30a4\uff01\u65e5\u672c\u9152\u306b\u604b\u3057\u305f\u5973\u305f\u3061\u300f\u4e88\u544a","languages":{"ja":{"youtube_id":"RLyoN5FNGNY","title":"\u6620\u753b\u300e\u30ab\u30f3\u30d1\u30a4\uff01\u65e5\u672c\u9152\u306b\u604b\u3057\u305f\u5973\u305f\u3061\u300f\u4e88\u544a"}}},{"group_id":1034101,"type":"trailer","title":"\u300e\u30ab\u30f3\u30d1\u30a4\uff01\u65e5\u672c\u9152\u306b\u604b\u3057\u305f\u5973\u305f\u3061\u300f\u6d77\u5916\u7248\u4e88\u544a","languages":{"ja":{"youtube_id":"67ZxzBtGapI","title":"\u300e\u30ab\u30f3\u30d1\u30a4\uff01\u65e5\u672c\u9152\u306b\u604b\u3057\u305f\u5973\u305f\u3061\u300f\u6d77\u5916\u7248\u4e88\u544a"}}}]}