{"imdb_id":"tt8171022","tmdb_id":515194,"title":"Ishq Tera","original_title":"Ishq Tera","year":2018,"release_date":null,"imdb_rating":6.1,"imdb_votes":40,"runtime":0,"overview":"ISHQ TERA is based on real life events of a woman with a broken mind and a man with a broken heart. The story of how men prey silently on this one disturbed Woman as her man fights to free her mind and win her heart - Again and again.","poster_path":"/zOeFse5RrcJJNyAKEJRM4Hp2LUK.jpg","backdrop_path":"/awFEsQlfARqozrrb9YKUFiCZ7gY.jpg","original_language":"hi","genres":["Romance"],"slug":"ishq-tera-2018-tt8171022","trailers":[{"youtube_id":"FGTi6r3HeDA","title":"Official Trailer (Broken)","type":"trailer","language":"en","region":"US","is_official":false,"published_at":"2018-03-21T11:06:22.000Z","quality":1080,"channel_name":"ISHQ TERA - the movie","duration":60,"views":1031966}],"trailer_groups":[{"group_id":1029614,"type":"trailer","title":"Official Trailer (Broken)","languages":{"en":{"youtube_id":"FGTi6r3HeDA","title":"Official Trailer (Broken)"}}}]}